{
  "title": "치과의사 치카뿡",
  "author": "신선웅",
  "illustrator": "윤공주",
  "isbn": "9788963832586",
  "publishedYear": 2011,
  "publisher": "별똥별",
  "paragraphInfoCount": 18,
  "paragraphInfo": [
    {
      "srcTextID": "117066",
      "srcText": "\"으앙, 싫어. 이를 빼는 건 무섭단 말이야.\" 치카뿡은 한서를 달래며 차근차근 설명했어요. \"흔들리는 이 밑에서 새 이가 나오려고 해.\"",
      "srcPage": 13,
      "srcSentenceEA": 4,
      "srcWordEA": 21,
      "character": "이,치카뿡,한서",
      "setting": null,
      "action": "달래며,설명했어요",
      "feeling": "무섭단 말이야",
      "causalRelationship": null,
      "outcomeResolution": null,
      "prediction": null,
      "plotSummaryInfoCount": 1,
      "plotSummaryInfo": {
        "classification": "신체운동_건강",
        "readAge": "유아",
        "form": "long-form",
        "plotSummaryText": "이를 빼는 건 무섭다고 말하자 치카뿡이 한서를 달래면서, 흔들리는 이 밑에서 새 이가 나오려 한다고 설명했습니다.",
        "textWordEA": 16
      }
    },
    {
      "srcTextID": "117065",
      "srcText": "\"내가 아프지 않게 한 번에 쏙 빼 줄게. 흔들리는 이를 제때 빼 주지 않으면 덧니가 될 수도 있는걸. 그럼 이를 닦기도 힘들어지고 못난이가 될 텐데.\" 한서는 못난이가 된다는 말에 덜컥 겁이 났어요.",
      "srcPage": 14,
      "srcSentenceEA": 4,
      "srcWordEA": 35,
      "character": "이,덧니,못난이,한서",
      "setting": null,
      "action": null,
      "feeling": "겁이 났어요",
      "causalRelationship": null,
      "outcomeResolution": null,
      "prediction": null,
      "plotSummaryInfoCount": 1,
      "plotSummaryInfo": {
        "classification": "신체운동_건강",
        "readAge": "유아",
        "form": "long-form",
        "plotSummaryText": "이를 제때 빼 주지 않으면 덧니가 될 수도 있고 이를 닦기도 힘들어 못난이가 된다는 말에 한서는 덜컥 겁이 났습니다.",
        "textWordEA": 19
      }
    },
    {
      "srcTextID": "117068",
      "srcText": "\"한서야, 치과가 무서운 곳인 줄 알았지? 우리 치과는 재미있는 곳이란다! 이렇게 예쁜 의자가 있는 건 몰랐지?\" 한서는 방긋 웃으며 의자에 누웠어요. 치카뿡은 이를 한 번에 쏙 빼 주었고요.",
      "srcPage": 15,
      "srcSentenceEA": 5,
      "srcWordEA": 32,
      "character": "한서,의자,치카뿡",
      "setting": "치과",
      "action": "웃으며,누웠어요,빼 주었고요",
      "feeling": null,
      "causalRelationship": null,
      "outcomeResolution": null,
      "prediction": null,
      "plotSummaryInfoCount": 1,
      "plotSummaryInfo": {
        "classification": "신체운동_건강",
        "readAge": "유아",
        "form": "long-form",
        "plotSummaryText": "우리 치과는 재미있는 곳이고 예쁜 의자도 있다는 말에 한서는 방긋 웃으며 의자에 누웠고, 치카뿡이 한 번에 이를 빼 주었습니다.",
        "textWordEA": 19
      }
    },
    {
      "srcTextID": "117054",
      "srcText": "꾸벅꾸벅, 뿌우웅 뿡! 치카뿡은 오늘도 졸면서 방귀를 뀌어요. 로봇 포포는 방귀 냄새에 머리가 어질어질했죠. \"어유, 냄새! 고기만 먹으니까 이렇게 냄새가 지독하지! 으, 방귀쟁이!\"",
      "srcPage": 1,
      "srcSentenceEA": 6,
      "srcWordEA": 27,
      "character": "치카뿡,로봇 포포,방귀쟁이",
      "setting": "오늘",
      "action": "졸면서,방귀를 뀌어요",
      "feeling": null,
      "causalRelationship": null,
      "outcomeResolution": null,
      "prediction": null,
      "plotSummaryInfoCount": 1,
      "plotSummaryInfo": {
        "classification": "신체운동_건강",
        "readAge": "유아",
        "form": "long-form",
        "plotSummaryText": "오늘도 치카뿡이 졸면서 방귀를 뀌자, 머리가 어질어질 했던 로봇 포포는 고기만 먹으니까 냄새가 지독하다고 말했습니다.",
        "textWordEA": 15
      }
    },
    {
      "srcTextID": "117061",
      "srcText": "치카뿡이 놀이터로 가 보니 아이는 이가 아파서 엉엉 울고 있어요. \"어쩌다가 이가 이렇게 많이 썩었니?\" 치카뿡의 물음에 친구들이 대신 대답했죠.",
      "srcPage": 7,
      "srcSentenceEA": 3,
      "srcWordEA": 21,
      "character": "치카뿡,아이,친구들",
      "setting": "놀이터",
      "action": "가 보니,울고 있어요,대답했죠",
      "feeling": null,
      "causalRelationship": null,
      "outcomeResolution": null,
      "prediction": null,
      "plotSummaryInfoCount": 1,
      "plotSummaryInfo": {
        "classification": "신체운동_건강",
        "readAge": "유아",
        "form": "short-form",
        "plotSummaryText": "치카뿡은 이가 아파서 울고 있는 아이에게 어쩌다가 이가 많이 썩었냐고 묻자, 친구들이 대신 대답했습니다.",
        "textWordEA": 14
      }
    },
    {
      "srcTextID": "117055",
      "srcText": "치카뿡은 빤딱별에서 이를 치료하는 치과 의사였어요. 하지만 어처구니없는 실수를 저질러서 쫓겨나고 말았죠. 글쎄, 치과를 무서워하는 왕자가 가까스로 온 날, 치카뿡이 뿌우웅, 지독한 방귀를 뀌었지 뭐예요. 왕자는 으앙, 울면서 뛰쳐나가 버렸답니다.",
      "srcPage": 2,
      "srcSentenceEA": 4,
      "srcWordEA": 33,
      "character": "치카뿡,치과 의사,왕자",
      "setting": "빤딱별",
      "action": "울면서,뛰쳐나가 버렸답니다.",
      "feeling": null,
      "causalRelationship": null,
      "outcomeResolution": null,
      "prediction": null,
      "plotSummaryInfoCount": 1,
      "plotSummaryInfo": {
        "classification": "신체운동_건강",
        "readAge": "유아",
        "form": "long-form",
        "plotSummaryText": "빤딱별에서 이를 치료하는 치과 의사였던 치카뿡은 왕자가 치과에 온 날 지독한 방귀를 뀌어서 쫓겨나고 말았습니다.",
        "textWordEA": 15
      }
    },
    {
      "srcTextID": "117056",
      "srcText": "이 말을 전해 들은 왕은 펄쩍펄쩍 뛰었어요. \"뭐라? 치과에 갔던 왕자가 치카뿡의 방귀 때문에 그냥 나왔다고?\" 불같이 화가 난 왕이 말했어요. \"치카뿡은 지구에 가서 착한 일 세 가지를 하여라. 그러기 전에는 돌아올 생각도 말라!\"",
      "srcPage": 3,
      "srcSentenceEA": 5,
      "srcWordEA": 37,
      "character": "왕,왕자,치카뿡,지구",
      "setting": "치과",
      "action": "전해 들은,펄쩍펄쩍 뛰었어요,말했어요",
      "feeling": "화가 난",
      "causalRelationship": null,
      "outcomeResolution": null,
      "prediction": null,
      "plotSummaryInfoCount": 1,
      "plotSummaryInfo": {
        "classification": "신체운동_건강",
        "readAge": "유아",
        "form": "long-form",
        "plotSummaryText": "치카뿡의 방귀 때문에 치과에 갔던 왕자가 그냥 나왔다는 말을 전해 듣고 화가 난 왕은 치카뿡에게 지구에 가서 착한 일 세 가지를 하기 전에는 못 돌아온다고 말했습니다.",
        "textWordEA": 26
      }
    },
    {
      "srcTextID": "117070",
      "srcText": "와! 어느새 치카뿡이 착한 일을 세 가지 했네요. 치카뿡은 환하게 웃으며 말했어요. \"포포, 내가 도와준 친구들이 고맙다고 할 때 마음이 뿌듯했어.\"",
      "srcPage": 16,
      "srcSentenceEA": 3,
      "srcWordEA": 23,
      "character": "치카뿡,포포,친구들",
      "setting": null,
      "action": "웃으며 말했어요",
      "feeling": null,
      "causalRelationship": null,
      "outcomeResolution": null,
      "prediction": null,
      "plotSummaryInfoCount": 1,
      "plotSummaryInfo": {
        "classification": "신체운동_건강",
        "readAge": "유아",
        "form": "short-form",
        "plotSummaryText": "치카뿡은 도와준 친구들이 고맙다고 할 때 마음이 뿌듯했다고, 포포에게 웃으며 말했습니다.",
        "textWordEA": 11
      }
    },
    {
      "srcTextID": "117064",
      "srcText": "다음 날에도 치카뿡은 요술 망원경으로 밖을 보았어요. \"포포, 한서한테 가 봐야겠어. 이를 빼지 않겠다고 울고불고 난리네.\" 치카뿡은 한서네 집으로 달려갔어요.",
      "srcPage": 11,
      "srcSentenceEA": 4,
      "srcWordEA": 22,
      "character": "치카뿡,요술 망원경,포포,한서,이",
      "setting": "다음 날,한서네 집",
      "action": "보았어요,달려갔어요",
      "feeling": null,
      "causalRelationship": null,
      "outcomeResolution": null,
      "prediction": null,
      "plotSummaryInfoCount": 1,
      "plotSummaryInfo": {
        "classification": "신체운동_건강",
        "readAge": "유아",
        "form": "long-form",
        "plotSummaryText": "요술 망원경으로 밖을 본 치카뿡은 이를 빼지 않겠다고 울고불고 난리인 한서네 집으로 달려갔습니다.",
        "textWordEA": 13
      }
    },
    {
      "srcTextID": "117060",
      "srcText": "\"애는 사탕을 무지 좋아해!\" \"초콜릿도 날마다 먹어!\" \"칫솔질도 잘 안 한대!\"",
      "srcPage": 8,
      "srcSentenceEA": 3,
      "srcWordEA": 11,
      "character": "얘,사탕,초콜릿",
      "setting": null,
      "action": "먹어",
      "feeling": "좋아해",
      "causalRelationship": null,
      "outcomeResolution": null,
      "prediction": null,
      "plotSummaryInfoCount": 1,
      "plotSummaryInfo": {
        "classification": "신체운동_건강",
        "readAge": "유아",
        "form": "short-form",
        "plotSummaryText": "얘는 사탕을 좋아하고 날마다 초콜릿도 먹는데, 칫솔질은 잘 안 한다고 말했습니다.",
        "textWordEA": 11
      }
    },
    {
      "srcTextID": "117063",
      "srcText": "치카뿡은 아이를 치과로 데려왔어요. \"조금만 참자. 썩은 이를 긁어내야 해. 치료가 끝나면 선물로 멋진 칫솔을 줄게.\"",
      "srcPage": 9,
      "srcSentenceEA": 4,
      "srcWordEA": 18,
      "character": "치카뿡,아이,칫솔",
      "setting": "치과",
      "action": "데려왔어요",
      "feeling": null,
      "causalRelationship": null,
      "outcomeResolution": null,
      "prediction": null,
      "plotSummaryInfoCount": 1,
      "plotSummaryInfo": {
        "classification": "신체운동_건강",
        "readAge": "유아",
        "form": "long-form",
        "plotSummaryText": "아이를 치과로 데려온 치카뿡은 썩은 이를 긁어내야 하며 치료가 끝나면 칫솔을 주겠다고 했습니다.",
        "textWordEA": 13
      }
    },
    {
      "srcTextID": "117062",
      "srcText": "\"어 어 으앙!\" 꾹꾹 잘 참던 아이가 울음을 터뜨렸을 때 스스슥! 치료가 끝났답니다. \"앞으로는 이를 잘 닦으렴. 초콜릿과 사탕도 조금씩만 먹고. 알았지?\" 아이는 치카뿡과 손가락을 걸고 약속했어요.",
      "srcPage": 10,
      "srcSentenceEA": 7,
      "srcWordEA": 32,
      "character": "아이,이,초콜릿,사탕,치카뿡",
      "setting": null,
      "action": "울음을 터뜨렸을,치료가 끝났답니다,손가락을 걸고 약속했어요",
      "feeling": null,
      "causalRelationship": null,
      "outcomeResolution": null,
      "prediction": null,
      "plotSummaryInfoCount": 1,
      "plotSummaryInfo": {
        "classification": "신체운동_건강",
        "readAge": "유아",
        "form": "long-form",
        "plotSummaryText": "아이가 울음을 터뜨렸을 때 치료가 끝났고, 치카뿡은 앞으로 이를 잘 닦으라며 아이와 손가락을 걸고 약속했습니다.",
        "textWordEA": 15
      }
    },
    {
      "srcTextID": "117069",
      "srcText": "\"지구에서 착한 일을 더 하고 싶어.\" \"와, 치카뿡! 그게 바로 보람이라는 거야. 그럼 앞으로도 이가 아픈 아이들을 찾아서 아프지 않게 치료해 줄 거야?\" \"당연하지!\"",
      "srcPage": 17,
      "srcSentenceEA": 4,
      "srcWordEA": 26,
      "character": "치카뿡,이,아이들",
      "setting": "지구",
      "action": null,
      "feeling": null,
      "causalRelationship": null,
      "outcomeResolution": null,
      "prediction": null,
      "plotSummaryInfoCount": 1,
      "plotSummaryInfo": {
        "classification": "신체운동_건강",
        "readAge": "유아",
        "form": "long-form",
        "plotSummaryText": "지구에서 착한 일을 더 하고 싶다는 치카뿡의 말에, 그게 보람이라는 것이며, 앞으로도 이가 아픈 아이들을 치료해 줄 거냐고 묻자 당연하다고 했습니다.",
        "textWordEA": 21
      }
    },
    {
      "srcTextID": "117071",
      "srcText": "이제 치카뿡은 방귀쟁이도 게으름뱅이도 아니에요. 지구에서도 빤딱별에서도 인정받는 치과 의사지요! 어린이 이 건강에 도움을 주어서 표창장도 받았어요. 치카뿡은 오늘도 요술 망원경으로 이가 아픈 아이들을 찾아내서 치료해 주었대요.",
      "srcPage": 18,
      "srcSentenceEA": 4,
      "srcWordEA": 30,
      "character": "치카뿡,방귀쟁이,게으름뱅이,치과 의사,어린이,이,요술 망원경",
      "setting": "지구,빤딱별",
      "action": "받았어요,찾아내서",
      "feeling": null,
      "causalRelationship": null,
      "outcomeResolution": null,
      "prediction": null,
      "plotSummaryInfoCount": 1,
      "plotSummaryInfo": {
        "classification": "신체운동_건강",
        "readAge": "유아",
        "form": "long-form",
        "plotSummaryText": "지구에서도 빤딱별에서도 인정받는 치과 의사인 치카뿡은 오늘도 요술 망원경으로 이가 아픈 아이들을 찾아내서 치료해 주었다고 합니다.",
        "textWordEA": 16
      }
    },
    {
      "srcTextID": "117067",
      "srcText": "뼈 속 영구치가 자라면서 젖니의 이뿌리에 닿으면 그 부분이 녹아 없어져요. 젖니가 흔들리고 영구치는 위로 더 올라와요. 젖니가 빠지고 영구치가 나와 뿌리를 더 단단하게 내려요.",
      "srcPage": 12,
      "srcSentenceEA": 3,
      "srcWordEA": 27,
      "character": "뼈,영구치,젖니",
      "setting": null,
      "action": "자라면서,닿으면,흔들리고,올라와요",
      "feeling": null,
      "causalRelationship": null,
      "outcomeResolution": null,
      "prediction": null,
      "plotSummaryInfoCount": 1,
      "plotSummaryInfo": {
        "classification": "신체운동_건강",
        "readAge": "유아",
        "form": "short-form",
        "plotSummaryText": "젖니가 흔들리고 영구치는 올라와서 젖니는 빠지고 영구치가 나와 뿌리를 단단하게 내립니다.",
        "textWordEA": 11
      }
    },
    {
      "srcTextID": "117058",
      "srcText": "치카뿡은 지구에서도 게으른 의사로 소문났어요. 보다 못한 포포가 말했어요. \"게으름뱅이 치카뿡! 착한 일은 언제 할 거야? 지난번에 딱 한 번 유치원에 가서 건강한 이에 대해 알려 준 것밖에 없잖아!\"",
      "srcPage": 4,
      "srcSentenceEA": 5,
      "srcWordEA": 32,
      "character": "치카뿡,의사,포포,게으름뱅이",
      "setting": "지구,유치원",
      "action": "말했어요",
      "feeling": null,
      "causalRelationship": null,
      "outcomeResolution": null,
      "prediction": null,
      "plotSummaryInfoCount": 1,
      "plotSummaryInfo": {
        "classification": "신체운동_건강",
        "readAge": "유아",
        "form": "long-form",
        "plotSummaryText": "지구에서도 게으른 의사로 소문난 치카뿡에게 착한 일은 언제 할 거냐고 포포가 말했습니다.",
        "textWordEA": 12
      }
    },
    {
      "srcTextID": "117057",
      "srcText": "사랑니가 나기 전 모습. 큰 어금니 음식을 갈아 줌. 작은 어금니 음식을 으깸. 송곳니 음식을 잘게 찢음. 앞니 음식을 자름.",
      "srcPage": 5,
      "srcSentenceEA": 5,
      "srcWordEA": 24,
      "character": "사랑니,큰 어금니,작은 어금니,송곳니,앞니",
      "setting": null,
      "action": "갈아 줌,으깸,잘게 찢음,자름",
      "feeling": null,
      "causalRelationship": null,
      "outcomeResolution": null,
      "prediction": null,
      "plotSummaryInfoCount": 1,
      "plotSummaryInfo": {
        "classification": "신체운동_건강",
        "readAge": "유아",
        "form": "long-form",
        "plotSummaryText": "어금니는 음식을 갈아주고 으깨는 역할을 하고, 송곳니와 음식을 잘게 찢고 앞니는  자르는 역할을 합니다.",
        "textWordEA": 15
      }
    },
    {
      "srcTextID": "117059",
      "srcText": "치카뿡이 느릿느릿 움직이며 말했어요. \"알았어. 착한 일을 찾아볼게.\" 치카뿡은 빤딱별에서 가져온 요술 망원경으로 병원 밖 놀이터를 보았어요. \"포포, 저기 이가 잔뜩 썩은 아이가 있어. 어서 가 보자!\"",
      "srcPage": 6,
      "srcSentenceEA": 5,
      "srcWordEA": 30,
      "character": "치카뿡,요술 망원경,포포,병원,아이",
      "setting": "빤딱별,놀이터",
      "action": "말했어요,가져온",
      "feeling": null,
      "causalRelationship": null,
      "outcomeResolution": null,
      "prediction": null,
      "plotSummaryInfoCount": 1,
      "plotSummaryInfo": {
        "classification": "신체운동_건강",
        "readAge": "유아",
        "form": "long-form",
        "plotSummaryText": "치카뿡은 빤딱별에서 가져온 요술 망원경으로  병원 밖 놀이터를 보았고, 이가 잔뜩 썩은 아이가 있다며  포포에게 가보자고 말했습니다.",
        "textWordEA": 19
      }
    }
  ]
}