{
  "title": "법정에서 만난 잭과 거인",
  "author": "정율희",
  "illustrator": "최은영",
  "isbn": "9791165957452",
  "publishedYear": 2023,
  "publisher": "아람북스",
  "paragraphInfoCount": 34,
  "paragraphInfo": [
    {
      "srcTextID": "4455",
      "srcText": "법정 안은 순식간에 소란스러워졌어요. 이번에는 꼼꼼한 변호인이 말했어요. 잭이 콩과 바꾼 소 한 마리는 잭의 집에 유일하게 남은 재산이었습니다. ",
      "srcPage": 5,
      "srcSentenceEA": 3,
      "srcWordEA": 21,
      "character": "꼼꼼한 변호인,잭,콩,소",
      "setting": "법정,잭의 집",
      "action": "소란스러워졌어요,말했어요,바꾼,유일하게 남은",
      "feeling": null,
      "causalRelationship": null,
      "outcomeResolution": null,
      "prediction": "잭이 콩과 바꾼 소 한 마리는 잭의 집에 유일하게 남은 재산이었습니다.",
      "plotSummaryInfoCount": 1,
      "plotSummaryInfo": {
        "classification": "사회관계",
        "readAge": "초등_고학년",
        "form": "short-form",
        "plotSummaryText": "변호인이 나서서 잭이 콩과 바꾼 소 한 마리는 잭의 집에 유일하게 남은 재산이었다고 말했습니다.",
        "textWordEA": 14
      }
    },
    {
      "srcTextID": "4450",
      "srcText": "이곳은 와글와글 법정이에요. “오늘은 또 무슨 일이야?” “잭이 도둑으로 고소가 되었대.”",
      "srcPage": 1,
      "srcSentenceEA": 3,
      "srcWordEA": 11,
      "character": "잭,도둑",
      "setting": "이곳,법정,오늘",
      "action": "고소가 되었대",
      "feeling": null,
      "causalRelationship": null,
      "outcomeResolution": null,
      "prediction": null,
      "plotSummaryInfoCount": 1,
      "plotSummaryInfo": {
        "classification": "사회관계",
        "readAge": "초등_고학년",
        "form": "short-form",
        "plotSummaryText": "와글와글 법정에서 잭이 도둑으로 고소가 되었다는 소식이 들렸습니다.",
        "textWordEA": 8
      }
    },
    {
      "srcTextID": "4458",
      "srcText": "“재, 재판장님. 드릴 말씀이.” 노인은 숨을 몰아쉬며 간신히 서 있었어요. 꼼꼼한 변호인이 재빨리 노인에게 뛰어가서 어떤 이야기를 듣더니 손을 번쩍 들었어요. “존경하는 재판장님, 이 노인을 증인으로 신청합니다.”",
      "srcPage": 11,
      "srcSentenceEA": 5,
      "srcWordEA": 30,
      "character": "재판장님,노인,꼼꼼한 변호인,증인",
      "setting": null,
      "action": "몰아쉬며,서 있었어요,뛰어가서,듣더니,들었어요,신청합니다",
      "feeling": null,
      "causalRelationship": "꼼꼼한 변호인이 재빨리 노인에게 뛰어가서 어떤 이야기를 듣더니 손을 번쩍 들었어요.",
      "outcomeResolution": null,
      "prediction": null,
      "plotSummaryInfoCount": 1,
      "plotSummaryInfo": {
        "classification": "사회관계",
        "readAge": "초등_고학년",
        "form": "long-form",
        "plotSummaryText": "꼼꼼한 변호인은 노인에게 뛰어가서 어떤 이야기를 듣더니 노인을 증인으로 신청한다고 말하였습니다.",
        "textWordEA": 11
      }
    },
    {
      "srcTextID": "4463",
      "srcText": "하지만 판사는 뒤늦게 온 노인을 증인으로 허락했어요. 노인은 증인석에 서더니 놀라운 이야기를 했어요. 그러니까 잭이 태어나기 전에 있었던 일입니다. ",
      "srcPage": 13,
      "srcSentenceEA": 3,
      "srcWordEA": 21,
      "character": "판사,노인,증인,증인석,잭",
      "setting": "뒤늦게,태어나기 전",
      "action": "온,허락했어요,서더니,이야기를 했어요",
      "feeling": "놀라운",
      "causalRelationship": null,
      "outcomeResolution": null,
      "prediction": null,
      "plotSummaryInfoCount": 1,
      "plotSummaryInfo": {
        "classification": "사회관계",
        "readAge": "초등_고학년",
        "form": "short-form",
        "plotSummaryText": "판사가 노인을 증인으로 허락하자, 노인은 잭이 태어나기 전에 있었던 일을 말하기 시작했습니다.",
        "textWordEA": 12
      }
    },
    {
      "srcTextID": "4460",
      "srcText": "이때 치밀한 검사가 벌떡 일어났지요. “무슨 소리요? 재판 도중에 증인이라니요? 재판장님, 절대 안 됩니다.”",
      "srcPage": 12,
      "srcSentenceEA": 4,
      "srcWordEA": 16,
      "character": "치밀한 검사,증인,재판장",
      "setting": "이때,재판 도중",
      "action": "일어났지요",
      "feeling": null,
      "causalRelationship": null,
      "outcomeResolution": null,
      "prediction": null,
      "plotSummaryInfoCount": 1,
      "plotSummaryInfo": {
        "classification": "사회관계",
        "readAge": "초등_고학년",
        "form": "long-form",
        "plotSummaryText": "치밀한 검사는 재판 도중에 증인 신청은 절대 안된다고 말하였습니다.",
        "textWordEA": 9
      }
    },
    {
      "srcTextID": "4462",
      "srcText": "잭의 할아버지가 키우던 거위 가운데 황금알을 낳는 거위가 있었어요. 그때 저 못된 거인이 거위를 훔치고 집까지 모두 부숴 버렸답니다. 그러니까 잭이 훔친 거위와 황금알은 처음부터 잭의 것이었어요.",
      "srcPage": 14,
      "srcSentenceEA": 3,
      "srcWordEA": 29,
      "character": "잭의 할아버지,거위,황금알을 낳는 거위,못된 거인,황금알",
      "setting": "그때,처음부터",
      "action": "키우던,훔치고,부숴 버렸답니다",
      "feeling": null,
      "causalRelationship": null,
      "outcomeResolution": "그러니까 잭이 훔친 거위와 황금알은 처음부터 잭의 것이었어요.",
      "prediction": null,
      "plotSummaryInfoCount": 1,
      "plotSummaryInfo": {
        "classification": "사회관계",
        "readAge": "초등_고학년",
        "form": "short-form",
        "plotSummaryText": "잭의 할아버지가 집에서 황금알을 낳는 거위를 키우고 있었고, 못된 거인이 거위를 훔쳤기 때문에 거위와 황금알은 처음부터 잭의 것이라고 말하였습니다.",
        "textWordEA": 19
      }
    },
    {
      "srcTextID": "4464",
      "srcText": "증인의 말을 끝까지 전해 들은 판사는 고개를 끄덕였지요. 치밀한 검사는 증인의 말이 사실이냐고 거인에게 물었어요. 하지만 거인은 한마디도 못 했어요.",
      "srcPage": 15,
      "srcSentenceEA": 3,
      "srcWordEA": 22,
      "character": "증인,판사,치밀한 검사,거인",
      "setting": null,
      "action": "전해 들은,고개를 끄덕였지요,물었어요,한마디도 못 했어요",
      "feeling": null,
      "causalRelationship": null,
      "outcomeResolution": null,
      "prediction": "하지만 거인은 한마디도 못 했어요.",
      "plotSummaryInfoCount": 1,
      "plotSummaryInfo": {
        "classification": "사회관계",
        "readAge": "초등_고학년",
        "form": "short-form",
        "plotSummaryText": "치밀한 검사는 증인의 말이 사실이냐고 거인에게 물었지만, 거인은 한마디도 못 했습니다.",
        "textWordEA": 11
      }
    },
    {
      "srcTextID": "4466",
      "srcText": "탕 탕 탕! “모든 것이 분명하게 밝혀졌습니다. 거위는 처음부터 잭의 것이었습니다.”“하지만 잭이 그 사실을 모르는 상황에서 거인의 집에 들어가 물건을 가져왔다면 이 또한 잘못입니다. 따라서 잭과 거인 두 사람 모두에게 잘못이 있기 때문에 서로 화해하고 거인은 고소를 취하하도록 하세요.” ",
      "srcPage": 16,
      "srcSentenceEA": 5,
      "srcWordEA": 42,
      "character": "거위,잭,물건,거인,모두",
      "setting": "처음부터,거인의 집",
      "action": "밝혀졌습니다,들어가,가져왔다면,화해하고,고소를 취하하도록 하세요",
      "feeling": null,
      "causalRelationship": "따라서 잭과 거인 두 사람 모두에게 잘못이 있기 때문에 서로 화해하고 거인은 고소를 취하하도록 하세요.",
      "outcomeResolution": null,
      "prediction": null,
      "plotSummaryInfoCount": 1,
      "plotSummaryInfo": {
        "classification": "사회관계",
        "readAge": "초등_고학년",
        "form": "long-form",
        "plotSummaryText": "잭과 거인 모두에게 잘못이 있으니 서로 화해하고, 고소를 취하하라고 말하였습니다.",
        "textWordEA": 10
      }
    },
    {
      "srcTextID": "4465",
      "srcText": "결국 거인은 고소하지 않기로 결정했지요. 잭과 잭의 엄마는 기쁨의 눈물을 흘렸어요. 법정에 있던 다른 사람들도 공정한 판사의 판결에 고개를 끄덕였어요. ",
      "srcPage": 17,
      "srcSentenceEA": 3,
      "srcWordEA": 22,
      "character": "거인,잭,잭의 엄마,다른 사람들,판사",
      "setting": "법정",
      "action": "고소하지 않기로,결정했지요,고개를 끄덕였어요",
      "feeling": "기쁨의 눈물을 흘렸어요",
      "causalRelationship": null,
      "outcomeResolution": null,
      "prediction": null,
      "plotSummaryInfoCount": 1,
      "plotSummaryInfo": {
        "classification": "사회관계",
        "readAge": "초등_고학년",
        "form": "short-form",
        "plotSummaryText": "거인은 고소하지 않기로 결정했고, 법정에 있던 다른 사람들도 공정한 판사의 판결에 동의했습니다.",
        "textWordEA": 12
      }
    },
    {
      "srcTextID": "4467",
      "srcText": "재판이 끝난 뒤 사람들은 잭의 이야기를 하며 다음 순서를 기다렸어요. 와글와글 법정만의 자랑인 ‘와글와글 토론회’가 열릴 시간이었거든요. 마침, 먼 나라를 여행하고 돌아온 한스가 그 나라에서 만난 원님 이야기를 꺼냈어요.",
      "srcPage": 18,
      "srcSentenceEA": 4,
      "srcWordEA": 32,
      "character": "사람들,잭,한스,원님",
      "setting": "재판이 끝난 뒤,법정,먼 나라,와글와글 토론회가 열릴 시간",
      "action": "이야기를 하며,기다렸어요,여행하고,돌아온,만난,이야기를 꺼냈어요",
      "feeling": null,
      "causalRelationship": null,
      "outcomeResolution": null,
      "prediction": null,
      "plotSummaryInfoCount": 1,
      "plotSummaryInfo": {
        "classification": "사회관계",
        "readAge": "초등_고학년",
        "form": "long-form",
        "plotSummaryText": "와글와글 토론회가 열리자 먼 나라를 여행하고 돌아온 한스가 여행 중에 만난 원님 이야기를 꺼냈습니다.",
        "textWordEA": 14
      }
    },
    {
      "srcTextID": "4470",
      "srcText": "치밀한 검사가 이 문제에 관심을 보이며 사람들에게 설명하기 시작했지요. 여러분, 여기 있는 한스가 직접 경험한 이야기입니다. 어떤 나라의 옷감 장수가 남의 무덤 앞에서 잠을 자다가 옷감을 잃어버렸다고 합니다. ",
      "srcPage": 19,
      "srcSentenceEA": 3,
      "srcWordEA": 30,
      "character": "치밀한 검사,사람들,한스,옷감 장수,옷감",
      "setting": "어떤 나라,남의 무덤 앞",
      "action": "관심을 보이며,설명하기 시작했지요,여기 있는,경험한,잠을 자다가,잃어버렸다고",
      "feeling": null,
      "causalRelationship": "어떤 나라의 옷감 장수가 남의 무덤 앞에서 잠을 자다가 옷감을 잃어버렸다고 합니다.",
      "outcomeResolution": null,
      "prediction": null,
      "plotSummaryInfoCount": 1,
      "plotSummaryInfo": {
        "classification": "사회관계",
        "readAge": "초등_고학년",
        "form": "short-form",
        "plotSummaryText": "치밀한 검사는 남의 무덤 앞에서 잠을 자다가 옷감을 잃어버린 어떤 옷감 장수의 이야기를 한스에게 듣고 사람들에게 설명하기 시작했습니다.",
        "textWordEA": 18
      }
    },
    {
      "srcTextID": "4469",
      "srcText": "그런데 그 마을을 다스리던 원님이 도둑을 잡겠다고 무덤의 망주석을 가져다가 매질했다고 합니다. 그 광경을 지켜보던 사람들이 웃었고, 원님은 자신을 비웃었다며 웃은 사람들에게 옷감을 바치라고 했답니다. 치밀한 검사는 더욱 큰 소리로 말을 이었어요. ",
      "srcPage": 20,
      "srcSentenceEA": 3,
      "srcWordEA": 34,
      "character": "원님,도둑,무덤,망주석,사람들,자신,옷감,치밀한 검사",
      "setting": "마을",
      "action": "다스리던,잡겠다고,가져다가,매질했다고,지켜보던,웃었고,바치라고,말을 이었어요",
      "feeling": null,
      "causalRelationship": "그런데 그 마을을 다스리던 원님이 도둑을 잡겠다고 무덤의 망주석을 가져다가 매질했다고 합니다.",
      "outcomeResolution": "그 광경을 지켜보던 사람들이 웃었고, 원님은 자신을 비웃었다며 웃은 사람들에게 옷감을 바치라고 했답니다.",
      "prediction": null,
      "plotSummaryInfoCount": 1,
      "plotSummaryInfo": {
        "classification": "사회관계",
        "readAge": "초등_고학년",
        "form": "short-form",
        "plotSummaryText": "원님이 도둑을 잡겠다고 무덤의 망주석을 가져다가 매질을 한 후, 이를 보고 웃은 사람들에게 자신을 비웃었다며 옷감을 바치라고 했습니다.",
        "textWordEA": 18
      }
    },
    {
      "srcTextID": "4468",
      "srcText": "“원님은 두 가지 잘못을 저질렀습니다. 첫 번째는 남의 무덤 망주석을 망가뜨린 손괴죄입니다.” 공정한 판사는 치밀한 검사의 말에 귀를 기울였어요. 흠, 손괴죄라.” “또 하나는 직권 남용을 했다는 점입니다.” 치밀한 검사의 말에 법정 안은 시끌벅적해졌어요. ",
      "srcPage": 21,
      "srcSentenceEA": 6,
      "srcWordEA": 37,
      "character": "원님,무덤,망주석,공정한 판사,치밀한 검사",
      "setting": "법정",
      "action": "잘못을 저질렀습니다,망가뜨린,귀를 기울였어요,직권 남용을 했다,시끌벅적해졌어요",
      "feeling": null,
      "causalRelationship": null,
      "outcomeResolution": null,
      "prediction": null,
      "plotSummaryInfoCount": 1,
      "plotSummaryInfo": {
        "classification": "사회관계",
        "readAge": "초등_고학년",
        "form": "long-form",
        "plotSummaryText": "치밀한 검사는 원님이 남의 무덤 망주석을 망가뜨린 손괴죄와 직권 남용을 하는 두 가지 잘못을 저질렀다고 말했습니다.",
        "textWordEA": 16
      }
    },
    {
      "srcTextID": "4471",
      "srcText": "탕 탕 탕! “조용히 하세요. 검사는 왜 직권 남용이라고 생각하는지 차근차근 설명해 보세요.” “원님은 구경하다가 웃은 사람들에게 비단이라는 아주 값비싼 옷감을 바치라고 했습니다. 그러지 않으면 곤장을 때리겠다고 했지요. 원님이라는 자리의 힘을 빌려서 많은 사람들에게 마음의 고통을 준 것입니다.”",
      "srcPage": 22,
      "srcSentenceEA": 6,
      "srcWordEA": 41,
      "character": "검사,원님,웃은 사람들,비단,옷감",
      "setting": null,
      "action": "조용히 하세요,생각하는지,설명해 보세요,구경하다가,바치라고 했습니다,곤장을 때리겠다,힘을 빌려서",
      "feeling": null,
      "causalRelationship": null,
      "outcomeResolution": "원님이라는 자리의 힘을 빌려서 많은 사람들에게 마음의 고통을 준 것입니다.",
      "prediction": null,
      "plotSummaryInfoCount": 1,
      "plotSummaryInfo": {
        "classification": "사회관계",
        "readAge": "초등_고학년",
        "form": "long-form",
        "plotSummaryText": "검사는 판사에게 웃은 사람들에게 값비싼 비단을 바치지 않으면 곤장을 때리겠다고 한 원님의 행동이 자리의 힘을 빌려서 많은 사람들에게 마음의 고통을 준 직권 남용이라고 설명했습니다.",
        "textWordEA": 24
      }
    },
    {
      "srcTextID": "4472",
      "srcText": "“제 생각도 같습니다.” 그때 한스가 앞으로 나섰어요. 그 나라에서 본 가난한 집의 이야기를 들어 보세요. ",
      "srcPage": 23,
      "srcSentenceEA": 3,
      "srcWordEA": 17,
      "character": "한스",
      "setting": "그 나라,가난한 집",
      "action": "앞으로 나섰어요,본,들어 보세요",
      "feeling": null,
      "causalRelationship": null,
      "outcomeResolution": null,
      "prediction": null,
      "plotSummaryInfoCount": 1,
      "plotSummaryInfo": {
        "classification": "사회관계",
        "readAge": "초등_고학년",
        "form": "short-form",
        "plotSummaryText": "한스는 본인 생각도 같다고 말하며 그 나라에서 본 가난한 집의 이야기를 시작했습니다.",
        "textWordEA": 12
      }
    },
    {
      "srcTextID": "4474",
      "srcText": "보리죽을 먹으며 겨우 살아가던 그 사람들은 비단을 구하지 못해 안절부절못했습니다. 도둑질이라도 하고 싶다고 말했어요. 한스의 말에 와글와글 법정 사람들은 고개를 끄덕였어요. ",
      "srcPage": 24,
      "srcSentenceEA": 3,
      "srcWordEA": 23,
      "character": "보리죽,사람들,비단,한스,와글와글 법정 사람들",
      "setting": null,
      "action": "먹으며,살아가던,구하지 못해,고개를 끄덕였어요,말했어요",
      "feeling": "안절부절못했습니다",
      "causalRelationship": null,
      "outcomeResolution": null,
      "prediction": null,
      "plotSummaryInfoCount": 1,
      "plotSummaryInfo": {
        "classification": "사회관계",
        "readAge": "초등_고학년",
        "form": "short-form",
        "plotSummaryText": "가난한 사람들이 비단을 구하지 못해 도둑질이라도 하고 싶어했다는 한스의 말에 법정 사람들은 고개를 끄덕였어요.",
        "textWordEA": 14
      }
    },
    {
      "srcTextID": "4473",
      "srcText": "그리고 치밀한 검사도 더욱 소리 높여 말했어요. “원님은 사람들에게 너무 심한 대가를 치르게 했습니다. 분명 직권 남용죄에 해당됩니다.”",
      "srcPage": 25,
      "srcSentenceEA": 3,
      "srcWordEA": 19,
      "character": "치밀한 검사,원님,사람들",
      "setting": null,
      "action": "말했어요,대가를 치르게 했습니다,해당됩니다",
      "feeling": null,
      "causalRelationship": null,
      "outcomeResolution": null,
      "prediction": null,
      "plotSummaryInfoCount": 1,
      "plotSummaryInfo": {
        "classification": "사회관계",
        "readAge": "초등_고학년",
        "form": "short-form",
        "plotSummaryText": "치밀한 검사도 원님의 행동이 분명 직권 남용죄에 해당된다고 소리 높여 말했습니다.",
        "textWordEA": 11
      }
    },
    {
      "srcTextID": "4475",
      "srcText": "“도둑을 잡은 다음 무덤의 망주석은 어떻게 되었나요?” “망주석은 제자리로 돌아왔습니다. 무덤의 자손에게는 마음고생을 했다고 원님이 비단을 주었고요.”",
      "srcPage": 28,
      "srcSentenceEA": 3,
      "srcWordEA": 18,
      "character": "도둑,망주석,무덤의 자손,원님,비단",
      "setting": "잡은 다음",
      "action": "돌아왔습니다,주었고요",
      "feeling": "마음고생을 했다고",
      "causalRelationship": null,
      "outcomeResolution": null,
      "prediction": null,
      "plotSummaryInfoCount": 1,
      "plotSummaryInfo": {
        "classification": "사회관계",
        "readAge": "초등_고학년",
        "form": "short-form",
        "plotSummaryText": "무덤의 망주석은 제자리로 돌아왔고 자손에게는 원님이 비단을 주었다고 말했습니다.",
        "textWordEA": 9
      }
    },
    {
      "srcTextID": "4479",
      "srcText": "꼼꼼한 변호인이 계속 물었어요. “그럼, 사람들에게 거둬들인 비단은 어떻게 되었나요?” “도둑을 잡은 다음 다시 사람들에게 돌려주었지요.”",
      "srcPage": 29,
      "srcSentenceEA": 3,
      "srcWordEA": 16,
      "character": "꼼꼼한 변호인,사람들,비단,도둑",
      "setting": null,
      "action": "물었어요,거둬들인,잡은,돌려주었지요",
      "feeling": null,
      "causalRelationship": null,
      "outcomeResolution": "도둑을 잡은 다음 다시 사람들에게 돌려주었지요.",
      "prediction": null,
      "plotSummaryInfoCount": 1,
      "plotSummaryInfo": {
        "classification": "사회관계",
        "readAge": "초등_고학년",
        "form": "short-form",
        "plotSummaryText": "꼼꼼한 변호인이 사람들에게 거둬들인 비단은 어떻게 되었냐고 묻자, 도둑을 잡은 다음 다시 사람들에게 돌려주었다고 말하였습니다.",
        "textWordEA": 15
      }
    },
    {
      "srcTextID": "4478",
      "srcText": "꼼꼼한 변호인은 이번엔 사람들을 향해 말했어요. “모두 잘 이해하셨을 것으로 압니다. 원님은 현명하게 일을 해결하도록 노력했습니다. 사람들이 구해 오는 비단 가운데 옷감 장수가 잃어버린 비단이 있을 거라고 생각한 원님의 지혜에 저는 오히려 박수를 보내고 싶은데요?” ",
      "srcPage": 30,
      "srcSentenceEA": 4,
      "srcWordEA": 37,
      "character": "꼼꼼한 변호인,사람들,모두,원님,비단,옷감 장수",
      "setting": "이번엔",
      "action": "말했어요,구해 오는,잃어버린,생각한,해결하도록,노력했습니다",
      "feeling": "박수를 보내고 싶은데요",
      "causalRelationship": null,
      "outcomeResolution": null,
      "prediction": null,
      "plotSummaryInfoCount": 1,
      "plotSummaryInfo": {
        "classification": "사회관계",
        "readAge": "초등_고학년",
        "form": "long-form",
        "plotSummaryText": "꼼꼼한 변호인은 잃어버린 비단을 찾기 위해 노력한 원님의 지혜에 박수를 보내고 싶다고 말했습니다.",
        "textWordEA": 13
      }
    },
    {
      "srcTextID": "4480",
      "srcText": "그럼, 오늘의 ‘와글와글 토론회’는 이것으로 마치도록 하겠습니다. 탕 탕 탕! 공정한 판사는 망치를 두드렸어요. ",
      "srcPage": 33,
      "srcSentenceEA": 4,
      "srcWordEA": 17,
      "character": "공정한 판사",
      "setting": "오늘",
      "action": "마치도록,두드렸어요",
      "feeling": null,
      "causalRelationship": null,
      "outcomeResolution": null,
      "prediction": null,
      "plotSummaryInfoCount": 1,
      "plotSummaryInfo": {
        "classification": "사회관계",
        "readAge": "초등_고학년",
        "form": "long-form",
        "plotSummaryText": "와글와글 토론회를 마치면서 공정한 판사는 망치를 두드렸습니다.",
        "textWordEA": 7
      }
    },
    {
      "srcTextID": "4481",
      "srcText": "그리고 마음속으로 생각했지요. ‘원님의 지혜가 놀랍군. 꼭 한번 만나 보고 싶어.’ ",
      "srcPage": 34,
      "srcSentenceEA": 3,
      "srcWordEA": 13,
      "character": "원님",
      "setting": null,
      "action": "생각했지요",
      "feeling": "놀랍군",
      "causalRelationship": null,
      "outcomeResolution": null,
      "prediction": "꼭 한번 만나 보고 싶어.",
      "plotSummaryInfoCount": 1,
      "plotSummaryInfo": {
        "classification": "사회관계",
        "readAge": "초등_고학년",
        "form": "short-form",
        "plotSummaryText": "지혜로운 원님을 꼭 한번 만나 보고 싶다고 생각했습니다.",
        "textWordEA": 8
      }
    },
    {
      "srcTextID": "4451",
      "srcText": "“아니, 콩나무를 키운 잭 말이야?” 마을 사람들은 고개를 갸웃거리며 법정으로 모여들었어요. 공정한 판사님이 입장하십니다. ",
      "srcPage": 2,
      "srcSentenceEA": 3,
      "srcWordEA": 16,
      "character": "콩나무,잭,마을 사람들,공정한 판사님",
      "setting": "법정",
      "action": "키운,고개를 갸웃거리며,모여들었어요,입장하십니다",
      "feeling": null,
      "causalRelationship": null,
      "outcomeResolution": null,
      "prediction": null,
      "plotSummaryInfoCount": 1,
      "plotSummaryInfo": {
        "classification": "사회관계",
        "readAge": "초등_고학년",
        "form": "short-form",
        "plotSummaryText": "마을 사람들은 고개를 갸웃거리며 법정으로 모여들었고, 공정한 판사님도 입장하였습니다.",
        "textWordEA": 9
      }
    },
    {
      "srcTextID": "4453",
      "srcText": "모두 일어서 주세요. 판사가 들어오자 소란스러웠던 법정 안이 조용해졌어요. 한쪽에는 도둑으로 몰린 잭이, 다른 쪽에는 잭을 고소한 거인이 있었지요. ",
      "srcPage": 3,
      "srcSentenceEA": 3,
      "srcWordEA": 21,
      "character": "모두,판사,도둑,잭,거인",
      "setting": "법정",
      "action": "일어서 주세요,들어오자,소란스러웠던,조용해졌어요,몰린,고소한",
      "feeling": null,
      "causalRelationship": null,
      "outcomeResolution": null,
      "prediction": null,
      "plotSummaryInfoCount": 1,
      "plotSummaryInfo": {
        "classification": "사회관계",
        "readAge": "초등_고학년",
        "form": "short-form",
        "plotSummaryText": "판사가 입장해서 조용해진 법정 한 쪽에는 도둑으로 몰린 잭이, 다른 쪽에는 잭을 고소한 거인이 있었습니다.",
        "textWordEA": 15
      }
    },
    {
      "srcTextID": "4456",
      "srcText": "아니, 꼼꼼한 변호인! 그게 말이 된다고 보십니까? 잭은 남의 재산을 몰래 가져갔습니다. ",
      "srcPage": 7,
      "srcSentenceEA": 3,
      "srcWordEA": 14,
      "character": "꼼꼼한 변호인,잭,남의 재산",
      "setting": null,
      "action": "보십니까,가져갔습니다",
      "feeling": null,
      "causalRelationship": null,
      "outcomeResolution": null,
      "prediction": "잭은 남의 재산을 몰래 가져갔습니다.",
      "plotSummaryInfoCount": 1,
      "plotSummaryInfo": {
        "classification": "사회관계",
        "readAge": "초등_고학년",
        "form": "short-form",
        "plotSummaryText": "꼼꼼한 변호인의 말에 잭이 남의 재산을 몰래 가져간 거라며 반박했습니다.",
        "textWordEA": 10
      }
    },
    {
      "srcTextID": "4457",
      "srcText": "어떤 이유에서든 그것은 도둑질입니다! 치밀한 검사의 말에 꼼꼼한 변호인은 풀이 죽었어요.“그러니까 제 말은 도둑질을 하려고 거인의 집에 일부러 들어간 게 아니라는 것입니다. 재판장님께서 잭이 얼마나 착한 아이인지 알아주셨으면 합니다.” 잭의 엄마는 잭의 뒤에서 흐느끼고 있었고, 꼬마 잭은 고개를 떨어뜨렸어요. ",
      "srcPage": 8,
      "srcSentenceEA": 5,
      "srcWordEA": 43,
      "character": "치밀한 검사,꼼꼼한 변호인,재판장님,잭,잭의 엄마",
      "setting": "거인의 집",
      "action": "도둑질을 하려고,들어간 게,알아주셨으면,고개를 떨어뜨렸어요",
      "feeling": "풀이 죽었어요",
      "causalRelationship": null,
      "outcomeResolution": null,
      "prediction": null,
      "plotSummaryInfoCount": 1,
      "plotSummaryInfo": {
        "classification": "사회관계",
        "readAge": "초등_고학년",
        "form": "long-form",
        "plotSummaryText": "꼼꼼한 변호인은 잭은 착한 아이이고, 도둑질을 하려고 거인의 집에 들어간 게 아니라고 재판장님께 말하였습니다.",
        "textWordEA": 14
      }
    },
    {
      "srcTextID": "4461",
      "srcText": "판사는 잭을 안쓰러운 눈으로 쳐다보았지만, 검사의 말이 맞다고 생각했어요. “그러면 판결을 내려야겠소.” 판사가 입을 열자 순식간에 법정 안이 조용해졌어요.",
      "srcPage": 9,
      "srcSentenceEA": 3,
      "srcWordEA": 20,
      "character": "판사,잭,검사",
      "setting": "법정",
      "action": "쳐다보았지만,내려야겠소,입을 열자,조용해졌어요",
      "feeling": "안쓰러운",
      "causalRelationship": null,
      "outcomeResolution": null,
      "prediction": null,
      "plotSummaryInfoCount": 1,
      "plotSummaryInfo": {
        "classification": "사회관계",
        "readAge": "초등_고학년",
        "form": "short-form",
        "plotSummaryText": "판사는 잭이 안쓰러웠지만 검사의 말이 맞다고 생각하며 판결을 내리겠다고 했어요.",
        "textWordEA": 10
      }
    },
    {
      "srcTextID": "4452",
      "srcText": "거인의 옆에 있던 치밀한 검사가 말했어요. “잭은 어머니에게 효도를 한다는 핑계로 거인의 집에 몰래 들어가 거인이 아끼던 황금알을 낳는 거위를 훔쳐 달아났습니다. 또 콩나무를 자르는 바람에 거인이 땅에 떨어져 큰 상처를 입었습니다. 따라서 잭을 절도죄와 상해죄로 기소합니다.” ",
      "srcPage": 4,
      "srcSentenceEA": 4,
      "srcWordEA": 39,
      "character": "거인,검사,잭,어머니,황금알을 낳는 거위,콩나무",
      "setting": "거인의 집,땅",
      "action": "말했어요,효도를 한다,몰래 들어가,아끼던,훔쳐 달아났습니다,자르는,떨어져,큰 상처를 입었습니다,기소합니다",
      "feeling": null,
      "causalRelationship": null,
      "outcomeResolution": null,
      "prediction": null,
      "plotSummaryInfoCount": 1,
      "plotSummaryInfo": {
        "classification": "사회관계",
        "readAge": "초등_고학년",
        "form": "long-form",
        "plotSummaryText": "검사는 거인의 집에 몰래 들어가 황금알을 낳는 거위를 훔쳤고, 콩나무를 잘라 땅에 떨어진 거인에게 큰 상처를 입힌 잭을 절도죄와 상해죄로 기소하였습니다.",
        "textWordEA": 21
      }
    },
    {
      "srcTextID": "4454",
      "srcText": "그런데 그렇게 바꾼 콩이 하루 만에 자랐지요. 그 위에 보물이 있었다면 누군들 탐이 나지 않겠습니까? 병든 어머니의 약값도 없는 상황에서 말이죠.",
      "srcPage": 6,
      "srcSentenceEA": 3,
      "srcWordEA": 23,
      "character": "콩,보물,누군들,병든 어머니",
      "setting": null,
      "action": "바꾼,자랐지요,있었다면,약값도 없는",
      "feeling": "탐이 나지 않겠습니까",
      "causalRelationship": null,
      "outcomeResolution": null,
      "prediction": null,
      "plotSummaryInfoCount": 1,
      "plotSummaryInfo": {
        "classification": "사회관계",
        "readAge": "초등_고학년",
        "form": "short-form",
        "plotSummaryText": "바꾼 콩은 하루 만에 자랐고, 그 위에 보물이 있었다면 누구라도 탐을 냈을 것이라고 말하였습니다.",
        "textWordEA": 14
      }
    },
    {
      "srcTextID": "4459",
      "srcText": "“효성이 아무리 지극하다 하여도 남의 물건을 훔치는 것은 잘못된 행동이오. 게다가.” 그때 법정 문이 벌컥 열렸어요. 머리가 하얀 노인이 지팡이를 들고 비틀거리며 들어왔지요. ",
      "srcPage": 10,
      "srcSentenceEA": 4,
      "srcWordEA": 26,
      "character": "남,물건,머리가 하얀 노인,지팡이",
      "setting": "그때,법정",
      "action": "훔치는,열렸어요,들고,비틀거리며,들어왔지요",
      "feeling": null,
      "causalRelationship": null,
      "outcomeResolution": null,
      "prediction": null,
      "plotSummaryInfoCount": 1,
      "plotSummaryInfo": {
        "classification": "사회관계",
        "readAge": "초등_고학년",
        "form": "long-form",
        "plotSummaryText": "효성이 깊어도 남의 물건을 훔치는 것은 잘못된 행동이라고 말하는 순간 머리가 하얀 노인이 법정으로 들어왔습니다.",
        "textWordEA": 15
      }
    },
    {
      "srcTextID": "4477",
      "srcText": "그때 꼼꼼한 변호인이 나섰어요. “제 생각은 다릅니다.” 꼼꼼한 변호인은 말을 이었어요. ",
      "srcPage": 26,
      "srcSentenceEA": 3,
      "srcWordEA": 12,
      "character": "꼼꼼한 변호인",
      "setting": "그때",
      "action": "나섰어요,말을 이었어요,다릅니다",
      "feeling": null,
      "causalRelationship": null,
      "outcomeResolution": null,
      "prediction": null,
      "plotSummaryInfoCount": 1,
      "plotSummaryInfo": {
        "classification": "사회관계",
        "readAge": "초등_고학년",
        "form": "short-form",
        "plotSummaryText": "꼼꼼한 변호인은 본인 생각은 다르다며 나서서 말을 이었습니다.",
        "textWordEA": 8
      }
    },
    {
      "srcTextID": "4476",
      "srcText": "“한스에게 묻고 싶은 게 있습니다. 비단을 훔쳐 간 도둑은 결국 잡았나요?” “네, 원님이 비단을 바치라고 한 덕분에 옷감 장수가 잃어버린 비단을 모두 찾아낼 수 있었지요.”",
      "srcPage": 27,
      "srcSentenceEA": 3,
      "srcWordEA": 26,
      "character": "한스,비단,도둑,원님,옷감 장수",
      "setting": null,
      "action": "묻고 싶은,훔쳐 간,잡았나요,바치라고,잃어버린,찾아낼 수",
      "feeling": null,
      "causalRelationship": null,
      "outcomeResolution": "네, 원님이 비단을 바치라고 한 덕분에 옷감 장수가 잃어버린 비단을 모두 찾아낼 수 있었지요.",
      "prediction": null,
      "plotSummaryInfoCount": 1,
      "plotSummaryInfo": {
        "classification": "사회관계",
        "readAge": "초등_고학년",
        "form": "short-form",
        "plotSummaryText": "비단을 훔쳐 간 도둑은 잡았냐는 질문에 한스는 원님이 비단을 바치라고 한 덕분에 옷감 장수는 잃어버린 비단을 모두 찾았다고 말했습니다.",
        "textWordEA": 19
      }
    },
    {
      "srcTextID": "4483",
      "srcText": "이야기를 듣던 판사가 드디어 입을 열었어요. 매우 흥미로운 이야기였습니다. 제 생각은 이렇습니다. ",
      "srcPage": 31,
      "srcSentenceEA": 3,
      "srcWordEA": 14,
      "character": "판사",
      "setting": null,
      "action": "듣던,열었어요",
      "feeling": "흥미로운",
      "causalRelationship": null,
      "outcomeResolution": null,
      "prediction": null,
      "plotSummaryInfoCount": 1,
      "plotSummaryInfo": {
        "classification": "사회관계",
        "readAge": "초등_고학년",
        "form": "short-form",
        "plotSummaryText": "흥미롭게 이야기를 듣던 판사가 입을 열었습니다.",
        "textWordEA": 6
      }
    },
    {
      "srcTextID": "4482",
      "srcText": "원님은 비록 지혜롭게 도둑을 잡았지만 도둑을 잡는 과정에서 손괴죄와 직권 남용죄를 저지른 것이 일부 인정됩니다. 하지만 죄에 대한 보상을 한 점도 인정되는군요. 따라서 우리는 원님의 지혜로운 부분만 본받는 게 좋을 듯합니다. ",
      "srcPage": 32,
      "srcSentenceEA": 3,
      "srcWordEA": 33,
      "character": "원님,도둑,우리",
      "setting": null,
      "action": "잡았지만,저지른,인정됩니다,본받는",
      "feeling": null,
      "causalRelationship": null,
      "outcomeResolution": "따라서 우리는 원님의 지혜로운 부분만 본받는 게 좋을 듯합니다.",
      "prediction": null,
      "plotSummaryInfoCount": 1,
      "plotSummaryInfo": {
        "classification": "사회관계",
        "readAge": "초등_고학년",
        "form": "short-form",
        "plotSummaryText": "도둑을 잡는 과정에서 손괴죄와 직권 남용죄를 저지른 것은 인정되지만 죄에 대한 보상을 한 점도 인정 되니 원님의 지혜로운 부분만 본받는 게 좋을 듯하다고 말하였습니다.",
        "textWordEA": 24
      }
    }
  ]
}