{
  "title": "최재천 박사님, 그러다 옷 버려요",
  "author": "김준영",
  "illustrator": "정하진",
  "isbn": "9791128220852",
  "publishedYear": 2018,
  "publisher": "아람북스",
  "paragraphInfoCount": 22,
  "paragraphInfo": [
    {
      "srcTextID": "964",
      "srcText": "둘은 애벌레를 잡느라 정신없었지. “박사님, 어릴 때 생각이 나네요. 그땐 벌레 한 마리만 있으면 시간 가는 줄 몰랐어요.”",
      "srcPage": 3,
      "srcSentenceEA": 3,
      "srcWordEA": 19,
      "character": "둘은,애벌레,박사님,벌레",
      "setting": "어릴 때,그땐",
      "action": "잡느라,생각이 나네요",
      "feeling": "정신없었지,시간 가는 줄 몰랐어요",
      "causalRelationship": null,
      "outcomeResolution": null,
      "prediction": null,
      "plotSummaryInfoCount": 1,
      "plotSummaryInfo": {
        "classification": "사회관계",
        "readAge": "초등_고학년",
        "form": "short-form",
        "plotSummaryText": "둘은 애벌레를 잡으며 어릴 때 벌레 한마리만 있으면 시간 가는 줄 몰라했던 일을 떠올렸다.",
        "textWordEA": 14
      }
    },
    {
      "srcTextID": "963",
      "srcText": "그러자 박사가 빙그레 웃으며 말했어. “어릴 적뿐인가? 나는 지금도 그렇다네.” 그 말을 듣고 최재천은 곰곰이 생각했어.",
      "srcPage": 4,
      "srcSentenceEA": 4,
      "srcWordEA": 18,
      "character": "박사,나,최재천",
      "setting": "어릴 적,지금도",
      "action": "빙그레 웃으며 말했어,말을 듣고,곰곰이 생각했어",
      "feeling": null,
      "causalRelationship": null,
      "outcomeResolution": null,
      "prediction": null,
      "plotSummaryInfoCount": 1,
      "plotSummaryInfo": {
        "classification": "사회관계",
        "readAge": "초등_고학년",
        "form": "long-form",
        "plotSummaryText": "어릴 적 뿐만 아니라 지금도 그렇다는 박사의 말에 최재천은 곰곰이 생각했다.",
        "textWordEA": 11
      }
    },
    {
      "srcTextID": "962",
      "srcText": " ‘그래……. 나도 자연을 연구하는 사람이 되는 거야. 에드먼즈 박사님처럼 말이야.’ 조지 에드먼즈 박사는 하루살이를 연구하는 박사예요. 이 무렵 최재천은 동물학과 학생이었는데 박사가 한국에 머무는 동안 따라다니며 도와주었지요.",
      "srcPage": 5,
      "srcSentenceEA": 5,
      "srcWordEA": 32,
      "character": "나,자연,사람,에드먼즈 박사님,조지 에드먼즈 박사,하루살이,박사,최재천,동물학과 학생",
      "setting": "한국",
      "action": "연구하는,머무는 동안,따라다니며,도와주었지요",
      "feeling": null,
      "causalRelationship": null,
      "outcomeResolution": null,
      "prediction": "최재천은 동물학과 학생이었는데 박사가 한국에 머무는 동안 따라다니며 도와주었지요",
      "plotSummaryInfoCount": 1,
      "plotSummaryInfo": {
        "classification": "사회관계",
        "readAge": "초등_고학년",
        "form": "long-form",
        "plotSummaryText": "동물학과 학생이었던 최재천은 조지 에드먼즈 박사가 한국에 머무는 동안 따라다니며 자연을 연구하는 사람이 되기로 결심했다.",
        "textWordEA": 15
      }
    },
    {
      "srcTextID": "965",
      "srcText": " 어느덧 박사가 한국을 떠날 날이 다가왔어. “저도 박사님처럼 동물을 공부하고 싶어요. 어떻게 하면 좋을까요?” ",
      "srcPage": 6,
      "srcSentenceEA": 3,
      "srcWordEA": 16,
      "character": "박사,저,박사님,동물",
      "setting": "한국,떠날 날",
      "action": "다가왔어,공부하고 싶어요",
      "feeling": "어떻게 하면 좋을까요?",
      "causalRelationship": null,
      "outcomeResolution": null,
      "prediction": "저도 박사님처럼 동물을 공부하고 싶어요.",
      "plotSummaryInfoCount": 1,
      "plotSummaryInfo": {
        "classification": "사회관계",
        "readAge": "초등_고학년",
        "form": "short-form",
        "plotSummaryText": "박사가 한국을 떠날 날이 다가오자 최재천은 박사에게 동물을 공부하고 싶은데 어떻게 하면 좋을지 물었다.",
        "textWordEA": 14
      }
    },
    {
      "srcTextID": "960",
      "srcText": "“에드먼즈 박사님! 그러다 옷 버려요!” 박사는 최재천의 말을 듣는 둥 마는 둥 하며 개울로 뛰어들었어. 그러고는 돌을 뒤집어 하루살이 애벌레를 찾기 시작했지.",
      "srcPage": 1,
      "srcSentenceEA": 4,
      "srcWordEA": 25,
      "character": "에드먼즈 박사,박사,옷,최재천,돌,하루살이 애벌레",
      "setting": "개울",
      "action": "옷 버려요,말을 듣는 둥 마는 둥,뛰어들었어,뒤집어,찾기 시작했지",
      "feeling": null,
      "causalRelationship": null,
      "outcomeResolution": null,
      "prediction": null,
      "plotSummaryInfoCount": 1,
      "plotSummaryInfo": {
        "classification": "사회관계",
        "readAge": "초등_고학년",
        "form": "long-form",
        "plotSummaryText": "최재천 박사는 개울로 뛰어들어 돌을 뒤집어가며 하루살이 애벌레는 찾기 시작했습니다.",
        "textWordEA": 10
      }
    },
    {
      "srcTextID": "966",
      "srcText": "“그렇다면 다른 나라에서 공부하는 것도 좋다네. 더 많은 동물을 연구할 수 있거든.” 최재천은 결심했어. 그러고 나서 몇 년 뒤, 미국으로 떠났지.",
      "srcPage": 7,
      "srcSentenceEA": 4,
      "srcWordEA": 24,
      "character": "동물,최재천",
      "setting": "다른 나라,몇 년 뒤,미국",
      "action": "공부하는,연구할 수 있거든,결심했어,떠났지",
      "feeling": "좋다네",
      "causalRelationship": "“그렇다면 다른 나라에서 공부하는 것도 좋다네. 더 많은 동물을 연구할 수 있거든.” 최재천은 결심했어. 그러고 나서 몇 년 뒤,미국으로 떠났지.",
      "outcomeResolution": null,
      "prediction": null,
      "plotSummaryInfoCount": 1,
      "plotSummaryInfo": {
        "classification": "사회관계",
        "readAge": "초등_고학년",
        "form": "long-form",
        "plotSummaryText": "다른 나라에서 공부하는 것도 좋다는 박사의 말에 최재천은몇 년 뒤, 미국으로 떠났다.",
        "textWordEA": 12
      }
    },
    {
      "srcTextID": "967",
      "srcText": " 최재천은 미국에서도 개미 한 마리 그냥 지나치지 않았어. 하루는 목공소 앞을 지날 때였지. ‘저 속에 벌레가 있을지도 몰라.’",
      "srcPage": 8,
      "srcSentenceEA": 3,
      "srcWordEA": 21,
      "character": "최재천,개미,벌레",
      "setting": "미국,하루,목공소 앞",
      "action": "그냥 지나치지 않았어,지날 때",
      "feeling": null,
      "causalRelationship": null,
      "outcomeResolution": null,
      "prediction": null,
      "plotSummaryInfoCount": 1,
      "plotSummaryInfo": {
        "classification": "사회관계",
        "readAge": "초등_고학년",
        "form": "short-form",
        "plotSummaryText": "최재천은 미국의 목공소를 지날 때에도 그냥 지나치는 일 없이,어디든지 벌레가 있을 수 있다는 생각을 갖고 탐구를 계속 했습니다.",
        "textWordEA": 18
      }
    },
    {
      "srcTextID": "968",
      "srcText": " 최재천은 톱밥 더미를 헤집었어. 앗, 놀랍게도 정말 벌레가 있지 뭐야? ‘고것 참 신기하게 생겼네.’ 최재천은 벌레를 연구실로 가져갔어.",
      "srcPage": 9,
      "srcSentenceEA": 4,
      "srcWordEA": 22,
      "character": "최재천,톱밥 더미,벌레",
      "setting": "연구실",
      "action": "헤집었어,생겼네,가져갔어",
      "feeling": "놀랍게도,신기하게",
      "causalRelationship": null,
      "outcomeResolution": null,
      "prediction": null,
      "plotSummaryInfoCount": 1,
      "plotSummaryInfo": {
        "classification": "사회관계",
        "readAge": "초등_고학년",
        "form": "long-form",
        "plotSummaryText": "최재천은 톱밥 더미를 헤집어서 발견한 벌레를 연구실로 가져갔어.",
        "textWordEA": 8
      }
    },
    {
      "srcTextID": "970",
      "srcText": "민벌레 몸길이 0.2센티미터. 나무껍질 틈에 살고, 눈 이 없음. 대신 더듬이가 발달함. ",
      "srcPage": 10,
      "srcSentenceEA": 3,
      "srcWordEA": 15,
      "character": "민벌레,더듬이,눈",
      "setting": "나무껍질 틈",
      "action": "살고,발달",
      "feeling": null,
      "causalRelationship": null,
      "outcomeResolution": null,
      "prediction": "민벌레 몸길이 0.2센티미터. 나무껍질 틈에 살고,눈 이 없음. 대신 더듬이가 발달함",
      "plotSummaryInfoCount": 1,
      "plotSummaryInfo": {
        "classification": "사회관계",
        "readAge": "초등_고학년",
        "form": "short-form",
        "plotSummaryText": "민벌레는 나무껍질 틈에 살며 눈과 이가 없는 대신 더듬이가 발달했다.",
        "textWordEA": 10
      }
    },
    {
      "srcTextID": "972",
      "srcText": "그러던 어느 날 최재천은 눈이 번쩍 뜨이는 안내문을 보았어. ‘정글? 그래, 정글로 가는 거야!’ 최재천은 정글에서 더 많은 민벌레를 만나고 싶었어. 신이 난 최재천은 정글로 떠날 준비를 했지.",
      "srcPage": 13,
      "srcSentenceEA": 5,
      "srcWordEA": 32,
      "character": "최재천,안내문,민벌레",
      "setting": "어느 날,정글",
      "action": "보았어,떠날 준비를 했지",
      "feeling": "눈이 번쩍 뜨이는,만나고 싶었어,신이 난",
      "causalRelationship": "최재천은 정글에서 더 많은 민벌레를 만나고 싶었어. 신이 난 최재천은 정글로 떠날 준비를 했지.",
      "outcomeResolution": null,
      "prediction": null,
      "plotSummaryInfoCount": 1,
      "plotSummaryInfo": {
        "classification": "사회관계",
        "readAge": "초등_고학년",
        "form": "long-form",
        "plotSummaryText": "어느 날 최재천은 안내문을 보고 정글에서 더 많은 민벌레를 만나고 싶다는 생각에 정글로 떠날 준비를 했다.",
        "textWordEA": 16
      }
    },
    {
      "srcTextID": "973",
      "srcText": " 드디어 정글에 도착한 최재천은 숨을 크게 들이쉬었어. 너무 더워서 땀이 비 오듯 흘렀지. 꼭 찜통 속에 있는 것 같았어. ",
      "srcPage": 14,
      "srcSentenceEA": 3,
      "srcWordEA": 22,
      "character": "최재천",
      "setting": "정글",
      "action": "도착한,숨을 크게 들이쉬었어,땀이 비 오듯 흘렀지",
      "feeling": "더워서,찜통 속에 있는 것 같았어",
      "causalRelationship": "너무 더워서 땀이 비 오듯 흘렀지",
      "outcomeResolution": null,
      "prediction": null,
      "plotSummaryInfoCount": 1,
      "plotSummaryInfo": {
        "classification": "사회관계",
        "readAge": "초등_고학년",
        "form": "short-form",
        "plotSummaryText": "정글에 도착한 최재천은 너무 더워서 꼭 찜통 속에 있는 것 같다고 생각했습니다.",
        "textWordEA": 12
      }
    },
    {
      "srcTextID": "974",
      "srcText": " 바스락! 나뭇잎 소리에 화들짝 놀라 뒤를 돌아보자, 도마뱀 한 마리가 나무에서 최재천을 내려다보고 있었지. “하하, 도마뱀이 맞이해 주다니 영광인걸.” 최재천은 기대에 부풀었어.",
      "srcPage": 15,
      "srcSentenceEA": 4,
      "srcWordEA": 25,
      "character": "나뭇잎,도마뱀,나무,최재천",
      "setting": "나무에서",
      "action": "뒤를 돌아보자,내려다보고 있었지,맞이해 주다니",
      "feeling": "놀라,영광인걸,기대에 부풀었어",
      "causalRelationship": null,
      "outcomeResolution": null,
      "prediction": null,
      "plotSummaryInfoCount": 1,
      "plotSummaryInfo": {
        "classification": "사회관계",
        "readAge": "초등_고학년",
        "form": "long-form",
        "plotSummaryText": "도마뱀 한 마리가 나무에서 내려다보고 있는 모습이 자신을 맞이해 준다는 생각에 기대에 부풀었다.",
        "textWordEA": 13
      }
    },
    {
      "srcTextID": "975",
      "srcText": "하지만 민벌레를 찾는 일은 쉽지 않았어. 최재천은 민벌레가 살 만한 썩은 나무를 찾아 헤맸지. 때로는 독뱀이 우글거렸고, 때로는 개미 떼가 공격했어. 그러다 썩은 나무를 발견하면 이렇게 외치곤 했지. “야호, 썩은 나무다. 민벌레 집이야!” 어이쿠, 뱀이다!",
      "srcPage": 16,
      "srcSentenceEA": 7,
      "srcWordEA": 40,
      "character": "민벌레,최재천,썩은 나무,독뱀,개미 떼,뱀",
      "setting": "민벌레 집",
      "action": "찾는,찾아 헤맸지,우글거렸고,공격했어,발견하면,외치곤 했지",
      "feeling": "쉽지 않았어",
      "causalRelationship": null,
      "outcomeResolution": null,
      "prediction": "야호,썩은 나무다. 민벌레 집이야!",
      "plotSummaryInfoCount": 1,
      "plotSummaryInfo": {
        "classification": "사회관계",
        "readAge": "초등_고학년",
        "form": "long-form",
        "plotSummaryText": "최재천은 독뱀과 개미 떼 때문에 민벌레를 찾는 것을 어려워 했습니다.",
        "textWordEA": 10
      }
    },
    {
      "srcTextID": "980",
      "srcText": " 최재천은 썩은 나무 위로 기어올랐어. 그러고는 조심스레 나무껍질을 벗기기 시작했지. 나무껍질 틈에 숨어 있던 민벌레들은 쏜살같이 달아났어. “이크!” 다른 나무껍질을 또 조심조심 벗겼지. “잡았다! 민벌레 씨, 우리 연구실로 이사 좀 갈까요?”",
      "srcPage": 17,
      "srcSentenceEA": 5,
      "srcWordEA": 36,
      "character": "최재천,나무껍질,나무껍질 틈,민벌레",
      "setting": "썩은 나무 위,연구실",
      "action": "나무 위로 기어올랐어,벗기기 시작했지,숨어 있던,달아났어,벗겼지,잡았다,이사",
      "feeling": null,
      "causalRelationship": null,
      "outcomeResolution": null,
      "prediction": "잡았다! 민벌레 씨,우리 연구실로 이사 좀 갈까요",
      "plotSummaryInfoCount": 1,
      "plotSummaryInfo": {
        "classification": "사회관계",
        "readAge": "초등_고학년",
        "form": "long-form",
        "plotSummaryText": "썩은 나무 위로 올라가서 나무껍질 틈에 숨어 있던 민벌레를 연구실로 가져갔다.",
        "textWordEA": 11
      }
    },
    {
      "srcTextID": "983",
      "srcText": "최재천은 현미경으로 민벌레 한 쌍을 살펴보았어. 1. 수컷이 더듬이로 암컷을 톡톡. 하지만 암컷은 본 체 만 체. ",
      "srcPage": 18,
      "srcSentenceEA": 4,
      "srcWordEA": 20,
      "character": "최재천,현미경,민벌레,수컷,더듬이,암컷",
      "setting": null,
      "action": "살펴보았어,본 체 만 체",
      "feeling": null,
      "causalRelationship": null,
      "outcomeResolution": "최재천은 현미경으로 민벌레 한 쌍을 살펴보았어",
      "prediction": null,
      "plotSummaryInfoCount": 1,
      "plotSummaryInfo": {
        "classification": "사회관계",
        "readAge": "초등_고학년",
        "form": "long-form",
        "plotSummaryText": "최재천은 현미경으로 민벌레 암,수 한 쌍을 살펴보았다.",
        "textWordEA": 7
      }
    },
    {
      "srcTextID": "982",
      "srcText": "2. 수컷의 목에서 혹이 쑥. 암컷도 수컷 곁으로 앙금앙금.  3.수컷 머리의 구멍에서 물 같은 방울이 퐁! 이 방울을 암컷이 쪽쪽. 4. 마침내 둘은 사랑을 나누지.",
      "srcPage": 19,
      "srcSentenceEA": 7,
      "srcWordEA": 33,
      "character": "수컷,목,혹,암컷,수컷 머리,구멍,물,방울",
      "setting": null,
      "action": "곁으로 앙금앙금,물 같은 방울이 퐁,쪽쪽,사랑을 나누지",
      "feeling": null,
      "causalRelationship": null,
      "outcomeResolution": "마침내 둘은 사랑을 나누지",
      "prediction": null,
      "plotSummaryInfoCount": 1,
      "plotSummaryInfo": {
        "classification": "사회관계",
        "readAge": "초등_고학년",
        "form": "long-form",
        "plotSummaryText": "수컷의 목에서 혹이 나오면 암컷이 수컷 곁으로 다가가고,수컷 머리에서 나오는 물 같은 방울을 암컷이 마시며 둘은 사랑을 나눈다.",
        "textWordEA": 18
      }
    },
    {
      "srcTextID": "984",
      "srcText": "최재천은 어딜 가나 민벌레 얘기뿐이었어. “얘들아, 오늘 또 새로운 걸 발견했어!” “아휴, 또 민벌레 얘기야?” “난 궁금해. 어서 얘기해 봐.” “글쎄, 민벌레가 말이야.”",
      "srcPage": 20,
      "srcSentenceEA": 6,
      "srcWordEA": 24,
      "character": "최재천,민벌레",
      "setting": "오늘",
      "action": "얘기뿐이었어,발견했어,얘기해 봐",
      "feeling": "궁금해",
      "causalRelationship": null,
      "outcomeResolution": null,
      "prediction": null,
      "plotSummaryInfoCount": 1,
      "plotSummaryInfo": {
        "classification": "사회관계",
        "readAge": "초등_고학년",
        "form": "long-form",
        "plotSummaryText": "최재천은 어딜 가나 민벌레 얘기뿐이었다.",
        "textWordEA": 5
      }
    },
    {
      "srcTextID": "987",
      "srcText": "최재천이 민벌레만 연구했느냐고? 천만에! 민벌레 말고도 재미난 동물이 얼마나 많은데! 나무 속에 집을 짓고 사는 아즈텍개미, 알에 이불을 덮어 주는 다듬이벌레, 나뭇잎으로 텐트를 만드는 텐트박쥐까지. 정글은 최재천의 거대한 연구실이었던 거야.",
      "srcPage": 21,
      "srcSentenceEA": 5,
      "srcWordEA": 34,
      "character": "최재천,민벌레,동물,나무,아즈텍개미,다듬이벌레,텐트박쥐",
      "setting": "정글,거대한 연구실",
      "action": "연구했느냐고,집을 짓고 사는,알에 이불을 덮어 주는,나뭇잎으로 텐트를 만드는",
      "feeling": "재미난 동물",
      "causalRelationship": null,
      "outcomeResolution": "정글은 최재천의 거대한 연구실이었던 거야",
      "prediction": null,
      "plotSummaryInfoCount": 1,
      "plotSummaryInfo": {
        "classification": "사회관계",
        "readAge": "초등_고학년",
        "form": "long-form",
        "plotSummaryText": "최재천은 정글에서 민벌레 뿐만 아니라,아즈텍 개미,다듬이 벌레,텐트박쥐까지 많은 동물들을 연구했다.",
        "textWordEA": 10
      }
    },
    {
      "srcTextID": "969",
      "srcText": " 정글에 많이 살고 있음. 이것 말고는 알려진 게 거의 없음. 네가 바로 민벌레구나. ",
      "srcPage": 11,
      "srcSentenceEA": 3,
      "srcWordEA": 16,
      "character": "민벌레",
      "setting": "정글",
      "action": "살고",
      "feeling": null,
      "causalRelationship": null,
      "outcomeResolution": null,
      "prediction": "이것 말고는 알려진 게 거의 없음",
      "plotSummaryInfoCount": 1,
      "plotSummaryInfo": {
        "classification": "사회관계",
        "readAge": "초등_고학년",
        "form": "short-form",
        "plotSummaryText": "정글에 많이 살고 있다는 것 외에는 알려진 게 거의 없는 벌레는 민벌레입니다.",
        "textWordEA": 12
      }
    },
    {
      "srcTextID": "971",
      "srcText": "좁쌀만 한데도 더듬이 하나는 근사한걸! 꼭 구슬을 꿰어 놓은 것 같아. 최재천은 현미경과 곤충책을 들여다보느라 날이 새는 줄도 몰랐어. ",
      "srcPage": 12,
      "srcSentenceEA": 3,
      "srcWordEA": 21,
      "character": "좁쌀,더듬이,구슬,최재천,현미경,곤충책",
      "setting": "날이 새는 줄도",
      "action": "꿰어,곤충책을 들여다 보느라",
      "feeling": "근사한걸",
      "causalRelationship": "최재천은 현미경과 곤충책을 들여다보느라 날이 새는 줄도 몰랐어.",
      "outcomeResolution": null,
      "prediction": null,
      "plotSummaryInfoCount": 1,
      "plotSummaryInfo": {
        "classification": "사회관계",
        "readAge": "초등_고학년",
        "form": "short-form",
        "plotSummaryText": "최재천은 현미경과 곤충책을 들여다보며,작지만 근사하고 구슬 같은 더듬이에 감탄했습니다.",
        "textWordEA": 9
      }
    },
    {
      "srcTextID": "961",
      "srcText": "“찾았다!” 박사는 애벌레를 손바닥에 올려놓고 어린아이처럼 기뻐했어. ‘고작 애벌레 하나에 저리 좋아하시다니.’ 고개를 갸웃하던 최재천도 엉겁결에 따라 들어갔지. ",
      "srcPage": 2,
      "srcSentenceEA": 3,
      "srcWordEA": 21,
      "character": "박사,애벌레,어린아이,최재천",
      "setting": null,
      "action": "손바닥에 올려놓고,고개를 갸웃하던,따라 들어갔지",
      "feeling": "기뻐했어,좋아하시다니,엉겁결에",
      "causalRelationship": null,
      "outcomeResolution": null,
      "prediction": null,
      "plotSummaryInfoCount": 1,
      "plotSummaryInfo": {
        "classification": "사회관계",
        "readAge": "초등_고학년",
        "form": "short-form",
        "plotSummaryText": "애벌레를 손바닥에 올려놓고 어린아이처럼 좋아하는 박사를 따라,최재천도 엉겁결에 따라 들어갔습니다.",
        "textWordEA": 10
      }
    },
    {
      "srcTextID": "990",
      "srcText": "최재천은 대학에서 학생들을 가르치며 여러 가지 일을 해. 여전히 재미난 동물이 보이면 그냥 지나치지 않지. “최재천 박사님, 그러다 옷 버리겠어요!” 학생들이 말려도 듣는 둥 마는 둥! 그 옛날 에드먼즈 박사처럼 말이야.\n",
      "srcPage": 22,
      "srcSentenceEA": 5,
      "srcWordEA": 34,
      "character": "최재천,학생,동물,최재천 박사님,옷,학생들,에드먼즈 박사",
      "setting": "대학에서,그 옛날",
      "action": "가르치며,일을 해,동물이 보이면,지나치지 않지,옷 버리겠어요,말려도,듣는 둥 마는 둥",
      "feeling": "재미난 동물",
      "causalRelationship": null,
      "outcomeResolution": "학생들을 가르치며 여러 가지 일을 해. 여전히 재미난 동물이 보이면 그냥 지나치지 않지",
      "prediction": "학생들이 말려도 듣는 둥 마는 둥! 그 옛날 에드먼즈 박사처럼 말이야",
      "plotSummaryInfoCount": 1,
      "plotSummaryInfo": {
        "classification": "사회관계",
        "readAge": "초등_고학년",
        "form": "long-form",
        "plotSummaryText": "최재천은 대학에서 학생들을 가르치며 그 옛날 에드먼즈 박사처럼 여전히 재미난 동물이 보이면 그냥 지나치지 않는다.",
        "textWordEA": 15
      }
    }
  ]
}