{
  "title": "버섯은 식물일까? 동물일까?",
  "author": "편대범",
  "illustrator": "오현아",
  "isbn": "9788956149561",
  "publishedYear": 2014,
  "publisher": "차일드아카데미",
  "paragraphInfoCount": 18,
  "paragraphInfo": [
    {
      "srcTextID": "150966",
      "srcText": "꽃식물은 왜 저마다 꽃을 피울까? 바로 씨앗을 맺기 위해서야. 그래야 자손을 퍼뜨릴 수 있거든.",
      "srcPage": 5,
      "srcSentenceEA": 3,
      "srcWordEA": 16,
      "character": "꽃식물,씨앗,자손",
      "setting": null,
      "action": "피울까",
      "feeling": null,
      "causalRelationship": null,
      "outcomeResolution": null,
      "prediction": null,
      "plotSummaryInfoCount": 1,
      "plotSummaryInfo": {
        "classification": "자연탐구",
        "readAge": "유아",
        "form": "short-form",
        "plotSummaryText": "꽃식물은 씨앗을 맺기 위해서 꽃을 피우는 것이고, 그래야 자손을 퍼뜨릴 수 있습니다.",
        "textWordEA": 12
      }
    },
    {
      "srcTextID": "150969",
      "srcText": "내 친구 능청이는 옥수수를 가장 좋아해. 오물오물 씹는 맛이 아주 고소하거든. 그런데 옥수수가 한해살이풀인 걸 아니? 봄에 옥수수 씨앗을 땅에 심으면 땅 위로 떡잎이 한 장 얼굴을 빼죽 내밀어. 이내 줄기와 잎은 기다랗게, 뿌리는 수염처럼 자라지. 붓꽃, 벼, 잔디, 보리 등도 마찬가지야.",
      "srcPage": 9,
      "srcSentenceEA": 6,
      "srcWordEA": 47,
      "character": "능청이,옥수수,떡잎,줄기,잎,뿌리,붓꽃,벼,잔디,보리",
      "setting": "땅",
      "action": "심으면,내밀어,자라지",
      "feeling": "좋아해",
      "causalRelationship": null,
      "outcomeResolution": null,
      "prediction": null,
      "plotSummaryInfoCount": 1,
      "plotSummaryInfo": {
        "classification": "자연탐구",
        "readAge": "유아",
        "form": "long-form",
        "plotSummaryText": "옥수수는 한해살이풀이고, 봄에 옥수수 씨앗을 땅에 심으면 땅 위로 떡잎이 한 장 얼굴을 내밀며, 이내 줄기와 잎은 기다랗게, 뿌리는 수염처럼 자라고, 붓꽃, 벼, 잔디, 보리 등도 마찬가지입니다.",
        "textWordEA": 27
      }
    },
    {
      "srcTextID": "150970",
      "srcText": "잎이 무성한 걸 보니 캘 때가 되었는걸! 굵은 알 하나만 먹어도 든든한 고구마는 열매가 아니라 땅속뿌리를 먹는 식물이야. 고구마 고구마는 싹이 트면 떡잎이 두 장 봉긋 올라와. 뿌리는 굵은 원뿌리에 실처럼 가는 곁뿌리가 나지. 민들레, 해바라기, 무 등도 그렇게 자라.",
      "srcPage": 10,
      "srcSentenceEA": 5,
      "srcWordEA": 44,
      "character": "잎,고구마,떡잎,뿌리,곁뿌리,민들레,해바라기,무,원뿌리",
      "setting": null,
      "action": "올라와,자라,나지",
      "feeling": null,
      "causalRelationship": null,
      "outcomeResolution": null,
      "prediction": null,
      "plotSummaryInfoCount": 1,
      "plotSummaryInfo": {
        "classification": "자연탐구",
        "readAge": "유아",
        "form": "long-form",
        "plotSummaryText": "고구마는 열매가 아니라 땅속뿌리를 먹는 식물이고, 싹이 트면 떡잎이 두 장 올라오며, 뿌리는 굵은 원뿌리에 실처럼 가는 곁뿌리가 납니다.",
        "textWordEA": 19
      }
    },
    {
      "srcTextID": "150973",
      "srcText": "민꽃식물은 꽃을 피우지 않아. 그래서 씨앗도, 열매도 맺지 못하지. 그럼 어떻게 자손을 퍼뜨리느냐고? 홀씨주머니에서 자란 홀씨로 자손을 늘려. 홀씨가 바람을 타고 날아가다가 땅에 떨어져서 살며시 뿌리를 내리거든. 고사리, 쇠뜨기, 고란초, 석송 등이 그래.",
      "srcPage": 13,
      "srcSentenceEA": 6,
      "srcWordEA": 38,
      "character": "민꽃식물,씨앗,열매,홀씨주머니,홀씨,고사리,쇠뜨기,고란초,석송",
      "setting": null,
      "action": "날아가다가,떨어져서,뿌리를 내리거든",
      "feeling": null,
      "causalRelationship": null,
      "outcomeResolution": null,
      "prediction": null,
      "plotSummaryInfoCount": 1,
      "plotSummaryInfo": {
        "classification": "자연탐구",
        "readAge": "유아",
        "form": "long-form",
        "plotSummaryText": "민꽃식물은 꽃을 피우지 않아서 씨앗도, 열매도 맺지 못하고, 홀씨주머니에서 자란 홀씨로 자손을 늘리는데, 홀씨가 바람을 타고 날아가다가 땅에 떨어져서 뿌리를 내리며, 고사리, 쇠뜨기, 고란초, 석송 등이 그렇습니다.",
        "textWordEA": 27
      }
    },
    {
      "srcTextID": "150977",
      "srcText": "참, 숲에 사는 특별한 친구를 소개할게. 언뜻 보면 식물 같지만 식물이 아니야. 스스로 양분을 만들지 못하거든.",
      "srcPage": 16,
      "srcSentenceEA": 3,
      "srcWordEA": 18,
      "character": "친구,식물,양분",
      "setting": "숲",
      "action": "소개할게,만들지 못하거든",
      "feeling": null,
      "causalRelationship": null,
      "outcomeResolution": null,
      "prediction": null,
      "plotSummaryInfoCount": 1,
      "plotSummaryInfo": {
        "classification": "자연탐구",
        "readAge": "유아",
        "form": "short-form",
        "plotSummaryText": "숲에 사는 특별한 친구를 소개할 텐데, 언뜻 보면 식물 같지만 스스로 양분을 만들지 못하므로 식물이 아닙니다.",
        "textWordEA": 16
      }
    },
    {
      "srcTextID": "150976",
      "srcText": "이런 생물을 ‘균류’라고 하는데, 바로 버섯과 곰팡이가 여기에 속해. 곰팡이나 버섯은 동물이나 식물의 몸에 붙어살아. 균류는 동물이나 식물의 몸에 붙어살면서 양분을 빨아들이고 홀씨로 자손을 퍼뜨린단다. ",
      "srcPage": 17,
      "srcSentenceEA": 4,
      "srcWordEA": 28,
      "character": "균류,버섯,곰팡이,동물,식물,홀씨,자손",
      "setting": null,
      "action": "붙어살아,빨아들이고,퍼뜨린단다",
      "feeling": null,
      "causalRelationship": null,
      "outcomeResolution": null,
      "prediction": null,
      "plotSummaryInfoCount": 1,
      "plotSummaryInfo": {
        "classification": "자연탐구",
        "readAge": "유아",
        "form": "long-form",
        "plotSummaryText": "이런 생물을 균류라고 하는데, 곰팡이나 버섯은 동물이나 식물의 몸에 붙어살면서 양분을 빨아들이고 홀씨로 자손을 퍼뜨립니다.",
        "textWordEA": 15
      }
    },
    {
      "srcTextID": "150979",
      "srcText": "숲에는 참 다양한 식물이 살고 있어. 숲을 건강하게 만드는 고마운 친구지. 만약 식물이 없다면 어떻게 될까?",
      "srcPage": 18,
      "srcSentenceEA": 3,
      "srcWordEA": 18,
      "character": "식물,친구",
      "setting": "숲",
      "action": "살고 있어",
      "feeling": "고마운",
      "causalRelationship": null,
      "outcomeResolution": null,
      "prediction": null,
      "plotSummaryInfoCount": 1,
      "plotSummaryInfo": {
        "classification": "자연탐구",
        "readAge": "유아",
        "form": "short-form",
        "plotSummaryText": "숲에는 참 다양한 식물이 살고 있고, 숲을 건강하게 만드는 고마운 친구들입니다.",
        "textWordEA": 11
      }
    },
    {
      "srcTextID": "150961",
      "srcText": "우리 숲에 온 걸 환영해! 안녕! 나는 귀염둥이 너구리 너치야. 우리 숲에 온 걸 환영해.",
      "srcPage": 1,
      "srcSentenceEA": 4,
      "srcWordEA": 18,
      "character": "나,너구리,너치",
      "setting": "숲",
      "action": "온 걸",
      "feeling": null,
      "causalRelationship": null,
      "outcomeResolution": null,
      "prediction": null,
      "plotSummaryInfoCount": 1,
      "plotSummaryInfo": {
        "classification": "자연탐구",
        "readAge": "유아",
        "form": "long-form",
        "plotSummaryText": "나는 귀염둥이 너구리 너치고, 우리 숲에 온 걸 환영합니다.",
        "textWordEA": 9
      }
    },
    {
      "srcTextID": "150962",
      "srcText": "이곳에서는 하루하루가 아주 바쁘게 돌아가. 들꽃에서부터 동물에 이르기까지, 수많은 생물이 옹기종기 모여서 자손을 퍼뜨리며 살아가거든. 그 가운데 식물 친구들을 한번 만나 볼래?",
      "srcPage": 2,
      "srcSentenceEA": 3,
      "srcWordEA": 24,
      "character": "들꽃,동물,생물,식물",
      "setting": "이곳에서",
      "action": "퍼뜨리며 살아가거든",
      "feeling": null,
      "causalRelationship": null,
      "outcomeResolution": null,
      "prediction": null,
      "plotSummaryInfoCount": 1,
      "plotSummaryInfo": {
        "classification": "자연탐구",
        "readAge": "유아",
        "form": "short-form",
        "plotSummaryText": "이곳에서는 하루하루가 아주 바쁘게 돌아가는데, 들꽃에서부터 동물에 이르기까지, 수많은 생물이 옹기종기 모여서 자손을 퍼뜨리며 살아가기 때문입니다.",
        "textWordEA": 16
      }
    },
    {
      "srcTextID": "150963",
      "srcText": "식물은 없어서는 안 될 숲의 소중한 친구야. 저마다 화려하게 꽃을 피우지. 반면에 수수하게 꽃을 피우는 식물도 있어.",
      "srcPage": 3,
      "srcSentenceEA": 3,
      "srcWordEA": 19,
      "character": "식물,친구,꽃",
      "setting": "숲",
      "action": "피우지",
      "feeling": null,
      "causalRelationship": null,
      "outcomeResolution": null,
      "prediction": null,
      "plotSummaryInfoCount": 1,
      "plotSummaryInfo": {
        "classification": "자연탐구",
        "readAge": "유아",
        "form": "short-form",
        "plotSummaryText": "식물은 없어서는 안 될 숲의 소중한 친구고, 저마다 화려하게 꽃을 피웁니다.",
        "textWordEA": 11
      }
    },
    {
      "srcTextID": "150965",
      "srcText": "꽃식물은 꽃이 진 뒤에 씨앗을 맺어. 씨앗을 땅에 심으면 파릇파릇 새싹이 움트지. 사과, 복숭아, 호박, 장미, 백합 등을 살펴보렴. 꽃이 진 자리에 알알이 맺힌 씨앗을 볼 수 있을 거야.",
      "srcPage": 6,
      "srcSentenceEA": 4,
      "srcWordEA": 32,
      "character": "꽃식물,씨앗,새싹,사과,복숭아,호박,장미,백합",
      "setting": "땅",
      "action": "심으면,움트지,살펴보렴",
      "feeling": null,
      "causalRelationship": null,
      "outcomeResolution": null,
      "prediction": null,
      "plotSummaryInfoCount": 1,
      "plotSummaryInfo": {
        "classification": "자연탐구",
        "readAge": "유아",
        "form": "long-form",
        "plotSummaryText": "꽃식물은 꽃이 진 뒤에 씨앗을 맺고, 씨앗을 땅에 심으면 파릇파릇 새싹이 움틉니다.",
        "textWordEA": 12
      }
    },
    {
      "srcTextID": "150967",
      "srcText": "꽃식물이 씨앗을 만드는 과정은 아주 신기해. 밑씨와 씨방이 자라서 씨앗과 열매를 맺거든. 그런데 씨방이 없어서 밑씨가 겉으로 드러난 식물도 있어. 이런 식물은 꽃가루가 밑씨에 붙어서 수분을 하고, 꽃이 수수해서 눈에 잘 띄지 않는단다. 은행나무, 소나무, 가문비나무가 그래.",
      "srcPage": 7,
      "srcSentenceEA": 5,
      "srcWordEA": 41,
      "character": "꽃식물,씨앗,밑씨,씨방,열매,식물,꽃가루,은행나무,소나무,가문비나무",
      "setting": null,
      "action": "맺거든,붙어서",
      "feeling": "신기해",
      "causalRelationship": null,
      "outcomeResolution": null,
      "prediction": null,
      "plotSummaryInfoCount": 1,
      "plotSummaryInfo": {
        "classification": "자연탐구",
        "readAge": "유아",
        "form": "long-form",
        "plotSummaryText": "꽃식물은 밑씨와 씨방이 자라서 씨앗과 열매를 맺는데, 씨방이 없어서 밑씨가 겉으로 드러난 식물도 있으며, 이런 식물은 꽃가루가 밑씨에 붙어서 수분을 하고, 꽃이 수수해서 눈에 잘 띄지 않으며, 은행나무, 소나무, 가문비나무가 있습니다.",
        "textWordEA": 31
      }
    },
    {
      "srcTextID": "150968",
      "srcText": "와, 주렁주렁 열린 주홍빛 감이 보이니? 감꽃은 밖으로 말린 꽃잎 속에 밑씨와 씨방을 품고 있어. 밑씨는 자라서 씨앗이 되고, 씨방은 열매가 되지. 이렇게 씨앗을 맺는 식물이 또 있어. 유칼리나무, 등나무, 개구리밥 등이 그렇단다.",
      "srcPage": 8,
      "srcSentenceEA": 5,
      "srcWordEA": 37,
      "character": "감,감꽃,밑씨,씨방,씨앗,열매,식물,유칼리나무,등나무,개구리밥",
      "setting": null,
      "action": "열린,품고 있어,자라서",
      "feeling": null,
      "causalRelationship": null,
      "outcomeResolution": null,
      "prediction": null,
      "plotSummaryInfoCount": 1,
      "plotSummaryInfo": {
        "classification": "자연탐구",
        "readAge": "유아",
        "form": "long-form",
        "plotSummaryText": "감꽃은 밖으로 말린 꽃잎 속에 밑씨와 씨방을 품고 있으며, 밑씨는 자라서 씨앗이 되고, 씨방은 열매가 됩니다.",
        "textWordEA": 16
      }
    },
    {
      "srcTextID": "150972",
      "srcText": "숲 아래 개울까지 울긋불긋 꼬까옷을 입었어. 도라지꽃, 국화, 유채꽃 등이 활짝 피었거든. 꽃잎을 가만히 들여다보렴.",
      "srcPage": 11,
      "srcSentenceEA": 3,
      "srcWordEA": 17,
      "character": "도라지꽃,국화,유채꽃,꽃잎",
      "setting": "숲,개울",
      "action": "피었거든,들여다보렴",
      "feeling": null,
      "causalRelationship": null,
      "outcomeResolution": null,
      "prediction": null,
      "plotSummaryInfoCount": 1,
      "plotSummaryInfo": {
        "classification": "자연탐구",
        "readAge": "유아",
        "form": "short-form",
        "plotSummaryText": "도라지꽃, 국화, 유채꽃 등이 활짝 피어서, 숲 아래 개울까지 울긋불긋 꼬까옷을 입었습니다.",
        "textWordEA": 12
      }
    },
    {
      "srcTextID": "150964",
      "srcText": "일 년 내내 푸른 소나무처럼 말이야. 이렇게 꽃을 피우는 식물을 ‘꽃식물’이라고 해. 아예 꽃을 피우지 않는 식물도 있는데, 이것을 ‘민꽃식물’이라고 한단다.",
      "srcPage": 4,
      "srcSentenceEA": 5,
      "srcWordEA": 25,
      "character": "소나무,꽃식물,민꽃식물",
      "setting": "일 년 내내",
      "action": null,
      "feeling": null,
      "causalRelationship": null,
      "outcomeResolution": null,
      "prediction": null,
      "plotSummaryInfoCount": 1,
      "plotSummaryInfo": {
        "classification": "자연탐구",
        "readAge": "유아",
        "form": "long-form",
        "plotSummaryText": "일 년 내내 푸른 소나무처럼, 꽃을 피우는 식물을 꽃식물이라고 하고, 아예 꽃을 피우지 않는 식물도 있는데, 이것을 민꽃식물이라고 합니다.",
        "textWordEA": 19
      }
    },
    {
      "srcTextID": "150974",
      "srcText": "숲의 깊숙한 곳은 그늘지고 축축해. 그래서 햇볕을 싫어하는 이끼가 바위나 나무 밑동에 찰싹 달라붙어서 자라. 이끼는 암그루와 수그루가 따로 있는데, 암그루에서 만든 홀씨로 자손을 늘려. 솔이끼처럼 뿌리, 줄기, 잎의 구분이 뚜렷한 것도 있고, 우산이끼처럼 뚜렷하지 않은 것도 있어.",
      "srcPage": 14,
      "srcSentenceEA": 4,
      "srcWordEA": 41,
      "character": "이끼,바위,나무,암그루,수그루,홀씨,자손,솔이끼,뿌리,줄기,잎,우산이끼",
      "setting": "숲",
      "action": "달라붙어서 자라,늘려",
      "feeling": null,
      "causalRelationship": null,
      "outcomeResolution": null,
      "prediction": null,
      "plotSummaryInfoCount": 1,
      "plotSummaryInfo": {
        "classification": "자연탐구",
        "readAge": "유아",
        "form": "long-form",
        "plotSummaryText": "숲의 깊숙한 곳은 그늘지고 축축해서 햇볕을 싫어하는 이끼가 바위나 나무 밑동에 달라붙어서 자라고, 이끼는 암그루와 수그루가 따로 있는데, 암그루에서 만든 홀씨로 자손을 늘리며, 솔이끼처럼 뿌리, 줄기, 잎의 구분이 뚜렷한 것도 있고, 우산이끼처럼 뚜렷하지 않은 것도 있습니다.",
        "textWordEA": 36
      }
    },
    {
      "srcTextID": "150971",
      "srcText": "벚꽃, 장미, 국화, 양지꽃 등은 꽃잎이 여러 장이야. 꽃이 질 때는 꽃잎이 한 장씩 떨어지지. 그런데 나팔꽃, 도라지꽃은 꽃잎이 하나로 붙어 있어. 꽃이 질 때도 꽃이 통째로 떨어진단다.",
      "srcPage": 12,
      "srcSentenceEA": 4,
      "srcWordEA": 31,
      "character": "벚꽃,장미,국화,양지꽃,꽃잎,나팔꽃,도라지꽃",
      "setting": null,
      "action": "떨어지지",
      "feeling": null,
      "causalRelationship": null,
      "outcomeResolution": null,
      "prediction": null,
      "plotSummaryInfoCount": 1,
      "plotSummaryInfo": {
        "classification": "자연탐구",
        "readAge": "유아",
        "form": "long-form",
        "plotSummaryText": "벚꽃, 장미, 국화, 양지꽃 등은 꽃잎이 여러 장이고, 꽃이 질 때는 꽃잎이 한 장씩 떨어지는데, 나팔꽃, 도라지꽃은 꽃잎이 하나로 붙어 있고, 꽃이 질 때도 꽃이 통째로 떨어집니다.",
        "textWordEA": 27
      }
    },
    {
      "srcTextID": "150975",
      "srcText": "숲을 조금 벗어나면 바닷가가 나와. 바닷속에는 미역, 다시마, 김, 파래 등의 식물이 스스로 양분을 만들어 살아가고 있어. 이런 식물을 ‘조류’라고 해. 조류도 민꽃식물이어서 홀씨로 번식해. 또 줄기나 뿌리가 따로 구분되어 있지 않고 몸 전체가 이파리처럼 생겼단다.",
      "srcPage": 15,
      "srcSentenceEA": 6,
      "srcWordEA": 41,
      "character": "미역,다시마,김,파래,조류,민꽃식물,줄기,뿌리,이파리",
      "setting": "숲,바닷가,바닷속",
      "action": "벗어나면,살아가고 있어,번식해",
      "feeling": null,
      "causalRelationship": null,
      "outcomeResolution": null,
      "prediction": null,
      "plotSummaryInfoCount": 1,
      "plotSummaryInfo": {
        "classification": "자연탐구",
        "readAge": "유아",
        "form": "long-form",
        "plotSummaryText": "바닷속에는 미역, 다시마, 김, 파래 등의 식물이 스스로 양분을 만들어 살아가고 있는데, 이런 식물을 조류라고 하고, 민꽃식물이어서 홀씨로 번식하며, 줄기나 뿌리가 따로 구분되어 있지 않습니다.",
        "textWordEA": 25
      }
    }
  ]
}